{"h_crr_ri_234_0_0":{"x":"-51","y":"41"},"h_crr_ri_234_1_0":{"x":"-45","y":"36"},"h_crr_ri_234_2_0":{"x":"-35","y":"30"},"h_crr_ri_234_3_0":{"x":"-25","y":"32"},"h_crr_ri_234_4_0":{"x":"-7","y":"36"},"h_crr_ri_234_5_0":{"x":"-10","y":"36"},"h_crr_ri_234_6_0":{"x":"-25","y":"21"},"h_crr_ri_234_7_0":{"x":"-27","y":"21"},"h_drk_ri_234_0_0":{"x":"-42","y":"59"},"h_drk_ri_234_1_0":{"x":"-43","y":"56"},"h_drk_ri_234_2_0":{"x":"-39","y":"53"},"h_drk_ri_234_3_0":{"x":"-28","y":"51"},"h_drk_ri_234_4_0":{"x":"-12","y":"54"},"h_drk_ri_234_5_0":{"x":"-2","y":"58"},"h_drk_ri_234_6_0":{"x":"-13","y":"61"},"h_drk_ri_234_7_0":{"x":"-39","y":"47"},"h_crr_ri_233_0_0":{"x":"-45","y":"48"},"h_crr_ri_233_1_0":{"x":"-46","y":"37"},"h_crr_ri_233_2_0":{"x":"-34","y":"35"},"h_crr_ri_233_3_0":{"x":"-26","y":"32"},"h_crr_ri_233_4_0":{"x":"-8","y":"36"},"h_crr_ri_233_5_0":{"x":"-11","y":"38"},"h_crr_ri_233_6_0":{"x":"-25","y":"21"},"h_crr_ri_233_7_0":{"x":"-27","y":"21"},"h_crr_ri_232_0_0":{"x":"-45","y":"47"},"h_crr_ri_232_1_0":{"x":"-45","y":"36"},"h_crr_ri_232_2_0":{"x":"-34","y":"34"},"h_crr_ri_232_3_0":{"x":"-26","y":"33"},"h_crr_ri_232_4_0":{"x":"-8","y":"35"},"h_crr_ri_232_5_0":{"x":"-11","y":"37"},"h_crr_ri_232_6_0":{"x":"-25","y":"21"},"h_crr_ri_232_7_0":{"x":"-27","y":"21"},"h_drk_ri_232_0_0":{"x":"-36","y":"62"},"h_drk_ri_232_1_0":{"x":"-43","y":"56"},"h_drk_ri_232_2_0":{"x":"-34","y":"54"},"h_drk_ri_232_3_0":{"x":"-26","y":"52"},"h_drk_ri_232_4_0":{"x":"-7","y":"54"},"h_drk_ri_232_5_0":{"x":"0","y":"56"},"h_drk_ri_232_6_0":{"x":"-3","y":"57"},"h_drk_ri_232_7_0":{"x":"-23","y":"39"},"h_crr_ri_231_0_0":{"x":"-50","y":"48"},"h_crr_ri_231_1_0":{"x":"-46","y":"43"},"h_crr_ri_231_2_0":{"x":"-34","y":"38"},"h_crr_ri_231_3_0":{"x":"-24","y":"40"},"h_crr_ri_231_4_0":{"x":"-7","y":"42"},"h_crr_ri_231_5_0":{"x":"-15","y":"44"},"h_crr_ri_231_6_0":{"x":"-25","y":"21"},"h_crr_ri_231_7_0":{"x":"-27","y":"21"},"h_drk_ri_231_0_0":{"x":"-38","y":"57"},"h_drk_ri_231_1_0":{"x":"-42","y":"54"},"h_drk_ri_231_2_0":{"x":"-35","y":"53"},"h_drk_ri_231_3_0":{"x":"-29","y":"50"},"h_drk_ri_231_4_0":{"x":"-14","y":"55"},"h_drk_ri_231_5_0":{"x":"-8","y":"53"},"h_drk_ri_231_6_0":{"x":"-15","y":"56"},"h_drk_ri_231_7_0":{"x":"-23","y":"39"},"h_crr_ri_230_7_0":{"x":"-44","y":"35"},"h_crr_ri_230_6_0":{"x":"-44","y":"35"},"h_crr_ri_230_5_0":{"x":"-15","y":"43"},"h_crr_ri_230_4_0":{"x":"-10","y":"43"},"h_crr_ri_230_3_0":{"x":"-26","y":"39"},"h_crr_ri_230_2_0":{"x":"-35","y":"37"},"h_crr_ri_230_1_0":{"x":"-46","y":"41"},"h_crr_ri_230_0_0":{"x":"-52","y":"46"},"h_crr_ri_229_7_0":{"x":"-43","y":"36"},"h_crr_ri_229_6_0":{"x":"-43","y":"34"},"h_crr_ri_229_5_0":{"x":"-7","y":"39"},"h_crr_ri_229_4_0":{"x":"1","y":"37"},"h_crr_ri_229_3_0":{"x":"-26","y":"35"},"h_crr_ri_229_2_0":{"x":"-35","y":"33"},"h_crr_ri_229_1_0":{"x":"-45","y":"38"},"h_crr_ri_229_0_0":{"x":"-49","y":"44"},"h_crr_ri_228_7_0":{"x":"-44","y":"33"},"h_crr_ri_228_6_0":{"x":"-44","y":"31"},"h_crr_ri_228_5_0":{"x":"-16","y":"41"},"h_crr_ri_228_4_0":{"x":"-10","y":"41"},"h_crr_ri_228_3_0":{"x":"-25","y":"38"},"h_crr_ri_228_2_0":{"x":"-35","y":"39"},"h_crr_ri_228_1_0":{"x":"-46","y":"39"},"h_crr_ri_228_0_0":{"x":"-44","y":"49"},"h_crr_ri_227_7_0":{"x":"-44","y":"36"},"h_crr_ri_227_6_0":{"x":"-44","y":"34"},"h_crr_ri_227_5_0":{"x":"-16","y":"41"},"h_crr_ri_227_4_0":{"x":"-10","y":"41"},"h_crr_ri_227_3_0":{"x":"-25","y":"38"},"h_crr_ri_227_2_0":{"x":"-35","y":"39"},"h_crr_ri_227_1_0":{"x":"-46","y":"39"},"h_crr_ri_227_0_0":{"x":"-44","y":"49"},"h_crr_ri_226_7_0":{"x":"-44","y":"35"},"h_crr_ri_226_6_0":{"x":"-44","y":"36"},"h_crr_ri_226_5_0":{"x":"-11","y":"36"},"h_crr_ri_226_4_0":{"x":"-4","y":"33"},"h_crr_ri_226_3_0":{"x":"-24","y":"30"},"h_crr_ri_226_2_0":{"x":"-34","y":"28"},"h_crr_ri_226_1_0":{"x":"-44","y":"34"},"h_crr_ri_226_0_0":{"x":"-51","y":"37"},"h_drk_ri_226_3_0":{"x":"-30","y":"48"},"h_drk_ri_226_2_0":{"x":"-38","y":"50"},"h_drk_ri_226_1_0":{"x":"-43","y":"52"},"h_drk_ri_226_0_0":{"x":"-43","y":"56"},"h_drk_ri_226_7_0":{"x":"-43","y":"53"},"h_drk_ri_226_6_0":{"x":"-15","y":"56"},"h_drk_ri_226_5_0":{"x":"-6","y":"52"},"h_drk_ri_226_4_0":{"x":"-9","y":"51"},"h_crr_ri_225_7_0":{"x":"-27","y":"21"},"h_crr_ri_225_6_0":{"x":"-25","y":"21"},"h_crr_ri_225_0_0":{"x":"-47","y":"43"},"h_crr_ri_225_2_0":{"x":"-32","y":"33"},"h_crr_ri_225_4_0":{"x":"-5","y":"34"},"h_crr_ri_225_3_0":{"x":"-24","y":"34"},"h_crr_ri_225_1_0":{"x":"-43","y":"38"},"h_crr_ri_225_5_0":{"x":"-10","y":"37"},"h_drk_ri_225_7_0":{"x":"-27","y":"21"},"h_drk_ri_225_6_0":{"x":"-14","y":"57"},"h_drk_ri_225_0_0":{"x":"-39","y":"59"},"h_drk_ri_225_2_0":{"x":"-37","y":"50"},"h_drk_ri_225_4_0":{"x":"-13","y":"52"},"h_drk_ri_225_3_0":{"x":"-27","y":"52"},"h_drk_ri_225_1_0":{"x":"-41","y":"56"},"h_drk_ri_225_5_0":{"x":"-7","y":"55"},"h_crr_ri_224_7_0":{"x":"-27","y":"21"},"h_crr_ri_224_6_0":{"x":"-25","y":"21"},"h_crr_ri_224_0_0":{"x":"-46","y":"39"},"h_crr_ri_224_4_0":{"x":"2","y":"33"},"h_crr_ri_224_2_0":{"x":"-28","y":"28"},"h_crr_ri_224_1_0":{"x":"-41","y":"34"},"h_crr_ri_224_3_0":{"x":"-18","y":"30"},"h_crr_ri_224_5_0":{"x":"-14","y":"36"},"h_crr_ri_223_7_0":{"x":"-27","y":"21"},"h_crr_ri_223_6_0":{"x":"-25","y":"21"},"h_crr_ri_223_0_0":{"x":"-47","y":"45"},"h_crr_ri_223_2_0":{"x":"-29","y":"34"},"h_crr_ri_223_4_0":{"x":"-8","y":"36"},"h_crr_ri_223_3_0":{"x":"-25","y":"31"},"h_crr_ri_223_1_0":{"x":"-46","y":"38"},"h_crr_ri_223_5_0":{"x":"-12","y":"36"},"h_drk_ri_223_7_0":{"x":"-27","y":"21"},"h_drk_ri_223_0_0":{"x":"-39","y":"59"},"h_drk_ri_223_6_0":{"x":"-12","y":"56"},"h_drk_ri_223_2_0":{"x":"-32","y":"52"},"h_drk_ri_223_4_0":{"x":"-14","y":"53"},"h_drk_ri_223_3_0":{"x":"-26","y":"49"},"h_drk_ri_223_1_0":{"x":"-41","y":"55"},"h_drk_ri_223_5_0":{"x":"-8","y":"54"},"h_crr_ri_222_7_0":{"x":"-27","y":"21"},"h_crr_ri_222_6_0":{"x":"-25","y":"21"},"h_crr_ri_222_0_0":{"x":"-49","y":"47"},"h_crr_ri_222_1_0":{"x":"-43","y":"45"},"h_crr_ri_222_4_0":{"x":"-6","y":"42"},"h_crr_ri_222_2_0":{"x":"-33","y":"38"},"h_crr_ri_222_3_0":{"x":"-23","y":"39"},"h_drk_ri_222_7_0":{"x":"-27","y":"21"},"h_drk_ri_222_6_0":{"x":"-13","y":"58"},"h_drk_ri_222_0_0":{"x":"-38","y":"60"},"h_drk_ri_222_1_0":{"x":"-38","y":"57"},"h_drk_ri_222_5_0":{"x":"-4","y":"57"},"h_drk_ri_222_2_0":{"x":"-36","y":"52"},"h_drk_ri_222_4_0":{"x":"-11","y":"54"},"h_drk_ri_222_3_0":{"x":"-28","y":"52"},"h_crr_ri_221_7_0":{"x":"-27","y":"21"},"h_crr_ri_221_6_0":{"x":"-25","y":"21"},"h_crr_ri_221_3_0":{"x":"-24","y":"31"},"h_crr_ri_221_4_0":{"x":"-8","y":"32"},"h_crr_ri_221_2_0":{"x":"-34","y":"29"},"h_crr_ri_221_1_0":{"x":"-46","y":"33"},"h_crr_ri_221_5_0":{"x":"-15","y":"33"},"h_crr_ri_221_0_0":{"x":"-45","y":"38"},"h_drk_ri_221_7_0":{"x":"-27","y":"21"},"h_drk_ri_221_6_0":{"x":"-12","y":"56"},"h_drk_ri_221_3_0":{"x":"-27","y":"48"},"h_drk_ri_221_4_0":{"x":"-14","y":"53"},"h_drk_ri_221_2_0":{"x":"-38","y":"50"},"h_drk_ri_221_1_0":{"x":"-44","y":"55"},"h_drk_ri_221_5_0":{"x":"-9","y":"54"},"h_drk_ri_221_0_0":{"x":"-38","y":"57"},"h_crr_ri_220_7_0":{"x":"-27","y":"21"},"h_crr_ri_220_6_0":{"x":"-25","y":"21"},"h_crr_ri_220_0_0":{"x":"-51","y":"45"},"h_crr_ri_220_1_0":{"x":"-45","y":"43"},"h_crr_ri_220_2_0":{"x":"-37","y":"38"},"h_crr_ri_220_4_0":{"x":"-8","y":"40"},"h_crr_ri_220_3_0":{"x":"-24","y":"40"},"h_crr_ri_220_5_0":{"x":"-12","y":"43"},"h_drk_ri_220_7_0":{"x":"-27","y":"21"},"h_drk_ri_220_6_0":{"x":"0","y":"56"},"h_drk_ri_220_0_0":{"x":"-36","y":"58"},"h_drk_ri_220_2_0":{"x":"-38","y":"52"},"h_drk_ri_220_1_0":{"x":"-41","y":"56"},"h_drk_ri_220_5_0":{"x":"1","y":"56"},"h_drk_ri_220_4_0":{"x":"-2","y":"53"},"h_crr_ri_219_7_0":{"x":"-27","y":"21"},"h_crr_ri_219_6_0":{"x":"-25","y":"21"},"h_crr_ri_219_5_0":{"x":"-9","y":"36"},"h_crr_ri_219_4_0":{"x":"-7","y":"36"},"h_crr_ri_219_2_0":{"x":"-33","y":"31"},"h_crr_ri_219_0_0":{"x":"-47","y":"40"},"h_crr_ri_219_3_0":{"x":"-26","y":"30"},"h_crr_ri_219_1_0":{"x":"-43","y":"34"},"h_drk_ri_219_7_0":{"x":"-27","y":"21"},"h_drk_ri_219_6_0":{"x":"-11","y":"56"},"h_drk_ri_219_5_0":{"x":"-5","y":"55"},"h_drk_ri_219_4_0":{"x":"-13","y":"52"},"h_drk_ri_219_2_0":{"x":"-38","y":"53"},"h_drk_ri_219_0_0":{"x":"-41","y":"58"},"h_drk_ri_219_3_0":{"x":"-27","y":"48"},"h_drk_ri_219_1_0":{"x":"-42","y":"55"},"h_crr_ri_218_7_0":{"x":"-27","y":"21"},"h_crr_ri_218_6_0":{"x":"-25","y":"21"},"h_crr_ri_218_5_0":{"x":"-8","y":"36"},"h_crr_ri_218_0_0":{"x":"-47","y":"46"},"h_crr_ri_218_3_0":{"x":"-22","y":"32"},"h_crr_ri_218_2_0":{"x":"-30","y":"35"},"h_crr_ri_218_1_0":{"x":"-42","y":"36"},"h_crr_ri_218_4_0":{"x":"-7","y":"38"},"h_drk_ri_218_7_0":{"x":"-34","y":"55"},"h_drk_ri_218_6_0":{"x":"-12","y":"65"},"h_drk_ri_218_5_0":{"x":"-5","y":"62"},"h_drk_ri_218_4_0":{"x":"-10","y":"58"},"h_drk_ri_218_2_0":{"x":"-36","y":"56"},"h_drk_ri_218_1_0":{"x":"-43","y":"59"},"h_drk_ri_218_3_0":{"x":"-26","y":"54"},"h_drk_ri_218_0_0":{"x":"-36","y":"63"},"h_crr_ri_217_2_0":{"x":"-33","y":"36"},"h_crr_ri_217_5_0":{"x":"-7","y":"46"},"h_crr_ri_217_3_0":{"x":"-24","y":"42"},"h_crr_ri_217_6_0":{"x":"-25","y":"21"},"h_crr_ri_217_7_0":{"x":"-27","y":"21"},"h_crr_ri_217_1_0":{"x":"-39","y":"44"},"h_crr_ri_217_0_0":{"x":"-38","y":"48"},"h_crr_ri_217_4_0":{"x":"-9","y":"39"},"h_crr_ri_216_0_0":{"x":"-53","y":"52"},"h_crr_ri_216_1_0":{"x":"-46","y":"45"},"h_crr_ri_216_2_0":{"x":"-35","y":"40"},"h_crr_ri_216_3_0":{"x":"-26","y":"42"},"h_crr_ri_216_4_0":{"x":"1","y":"46"},"h_crr_ri_216_5_0":{"x":"-4","y":"46"},"h_crr_ri_216_6_0":{"x":"-25","y":"21"},"h_crr_ri_216_7_0":{"x":"-27","y":"21"},"h_crr_ri_215_7_0":{"x":"-44","y":"36"},"h_crr_ri_215_6_0":{"x":"-44","y":"37"},"h_crr_ri_215_5_0":{"x":"5","y":"38"},"h_crr_ri_215_4_0":{"x":"11","y":"35"},"h_crr_ri_215_3_0":{"x":"-23","y":"33"},"h_crr_ri_215_2_0":{"x":"-34","y":"28"},"h_crr_ri_215_1_0":{"x":"-46","y":"36"},"h_crr_ri_215_0_0":{"x":"-52","y":"45"},"h_crr_ri_214_7_0":{"x":"-27","y":"21"},"h_crr_ri_214_6_0":{"x":"-25","y":"21"},"h_crr_ri_214_5_0":{"x":"-12","y":"44"},"h_crr_ri_214_4_0":{"x":"-7","y":"43"},"h_crr_ri_214_3_0":{"x":"-24","y":"39"},"h_crr_ri_214_2_0":{"x":"-32","y":"37"},"h_crr_ri_214_1_0":{"x":"-45","y":"42"},"h_crr_ri_214_0_0":{"x":"-50","y":"47"},"h_drk_ri_214_7_0":{"x":"-34","y":"55"},"h_drk_ri_214_6_0":{"x":"-14","y":"58"},"h_drk_ri_214_5_0":{"x":"-5","y":"54"},"h_drk_ri_214_4_0":{"x":"-10","y":"54"},"h_drk_ri_214_3_0":{"x":"-27","y":"53"},"h_drk_ri_214_2_0":{"x":"-35","y":"52"},"h_drk_ri_214_1_0":{"x":"-38","y":"56"},"h_drk_ri_214_0_0":{"x":"-33","y":"59"},"h_crr_ri_213_7_0":{"x":"-27","y":"21"},"h_crr_ri_213_6_0":{"x":"-25","y":"21"},"h_crr_ri_213_5_0":{"x":"-12","y":"42"},"h_crr_ri_213_4_0":{"x":"-7","y":"41"},"h_crr_ri_213_3_0":{"x":"-24","y":"37"},"h_crr_ri_213_2_0":{"x":"-32","y":"35"},"h_crr_ri_213_1_0":{"x":"-45","y":"40"},"h_crr_ri_213_0_0":{"x":"-50","y":"45"},"h_drk_ri_213_7_0":{"x":"-34","y":"55"},"h_drk_ri_213_6_0":{"x":"-14","y":"58"},"h_drk_ri_213_5_0":{"x":"-5","y":"54"},"h_drk_ri_213_4_0":{"x":"-10","y":"55"},"h_drk_ri_213_3_0":{"x":"-27","y":"52"},"h_drk_ri_213_2_0":{"x":"-36","y":"53"},"h_drk_ri_213_1_0":{"x":"-40","y":"56"},"h_drk_ri_213_0_0":{"x":"-35","y":"59"},"h_drk_ri_212_0_0":{"x":"-38","y":"60"},"h_drk_ri_212_1_0":{"x":"-39","y":"58"},"h_drk_ri_212_2_0":{"x":"-36","y":"53"},"h_drk_ri_212_3_0":{"x":"-28","y":"52"},"h_drk_ri_212_4_0":{"x":"-2","y":"55"},"h_drk_ri_212_5_0":{"x":"1","y":"59"},"h_drk_ri_212_6_0":{"x":"-22","y":"21"},"h_drk_ri_212_7_0":{"x":"-23","y":"21"},"h_crr_ri_212_0_0":{"x":"-52","y":"47"},"h_crr_ri_212_1_0":{"x":"-46","y":"43"},"h_crr_ri_212_2_0":{"x":"-35","y":"37"},"h_crr_ri_212_3_0":{"x":"-25","y":"40"},"h_crr_ri_212_4_0":{"x":"-7","y":"42"},"h_crr_ri_212_5_0":{"x":"-11","y":"44"},"h_drk_ri_211_0_0":{"x":"-38","y":"60"},"h_drk_ri_211_1_0":{"x":"-39","y":"58"},"h_drk_ri_211_2_0":{"x":"-36","y":"53"},"h_drk_ri_211_3_0":{"x":"-28","y":"52"},"h_drk_ri_211_4_0":{"x":"-2","y":"55"},"h_drk_ri_211_5_0":{"x":"1","y":"59"},"h_drk_ri_211_6_0":{"x":"-22","y":"21"},"h_drk_ri_211_7_0":{"x":"-23","y":"21"},"h_crr_ri_211_0_0":{"x":"-52","y":"47"},"h_crr_ri_211_1_0":{"x":"-46","y":"43"},"h_crr_ri_211_2_0":{"x":"-35","y":"37"},"h_crr_ri_211_3_0":{"x":"-25","y":"40"},"h_crr_ri_211_4_0":{"x":"-7","y":"42"},"h_crr_ri_211_5_0":{"x":"-11","y":"44"},"h_drk_ri_210_0_0":{"x":"-38","y":"60"},"h_drk_ri_210_1_0":{"x":"-39","y":"58"},"h_drk_ri_210_2_0":{"x":"-36","y":"53"},"h_drk_ri_210_3_0":{"x":"-28","y":"52"},"h_drk_ri_210_4_0":{"x":"-2","y":"55"},"h_drk_ri_210_5_0":{"x":"1","y":"59"},"h_drk_ri_210_6_0":{"x":"-22","y":"21"},"h_drk_ri_210_7_0":{"x":"-23","y":"21"},"h_crr_ri_210_0_0":{"x":"-52","y":"47"},"h_crr_ri_210_1_0":{"x":"-46","y":"43"},"h_crr_ri_210_2_0":{"x":"-35","y":"37"},"h_crr_ri_210_3_0":{"x":"-25","y":"40"},"h_crr_ri_210_4_0":{"x":"-7","y":"42"},"h_crr_ri_210_5_0":{"x":"-11","y":"44"},"h_drk_ri_209_0_0":{"x":"-41","y":"64"},"h_drk_ri_209_1_0":{"x":"-46","y":"61"},"h_drk_ri_209_2_0":{"x":"-39","y":"56"},"h_drk_ri_209_3_0":{"x":"-26","y":"53"},"h_drk_ri_209_4_0":{"x":"17","y":"55"},"h_drk_ri_209_5_0":{"x":"-6","y":"60"},"h_drk_ri_209_6_0":{"x":"-15","y":"63"},"h_drk_ri_209_7_0":{"x":"-32","y":"60"},"h_crr_ri_209_0_0":{"x":"-46","y":"43"},"h_crr_ri_209_1_0":{"x":"-42","y":"37"},"h_crr_ri_209_2_0":{"x":"-32","y":"32"},"h_crr_ri_209_3_0":{"x":"-23","y":"31"},"h_crr_ri_209_4_0":{"x":"-7","y":"35"},"h_crr_ri_209_5_0":{"x":"-5","y":"37"},"h_crr_ri_209_6_0":{"x":"-25","y":"21"},"h_crr_ri_209_7_0":{"x":"-27","y":"21"},"h_crr_ri_208_0_0":{"x":"-51","y":"57"},"h_crr_ri_208_1_0":{"x":"-44","y":"54"},"h_crr_ri_208_2_0":{"x":"-33","y":"49"},"h_crr_ri_208_3_0":{"x":"-24","y":"50"},"h_crr_ri_208_4_0":{"x":"-8","y":"52"},"h_crr_ri_208_5_0":{"x":"-15","y":"55"},"h_crr_ri_208_6_0":{"x":"-25","y":"21"},"h_crr_ri_208_7_0":{"x":"-27","y":"21"},"h_drk_ri_208_0_0":{"x":"-28","y":"59"},"h_drk_ri_208_1_0":{"x":"-38","y":"62"},"h_drk_ri_208_2_0":{"x":"-34","y":"56"},"h_drk_ri_208_3_0":{"x":"-30","y":"58"},"h_drk_ri_208_4_0":{"x":"-11","y":"56"},"h_drk_ri_208_5_0":{"x":"-6","y":"61"},"h_drk_ri_208_6_0":{"x":"-9","y":"58"},"h_drk_ri_208_7_0":{"x":"-33","y":"50"},"h_crr_ri_207_0_0":{"x":"-45","y":"46"},"h_crr_ri_207_1_0":{"x":"-44","y":"41"},"h_crr_ri_207_2_0":{"x":"-33","y":"36"},"h_crr_ri_207_3_0":{"x":"-24","y":"38"},"h_crr_ri_207_4_0":{"x":"-9","y":"40"},"h_crr_ri_207_5_0":{"x":"-7","y":"43"},"h_crr_ri_207_6_0":{"x":"-47","y":"42"},"h_crr_ri_207_7_0":{"x":"-49","y":"38"},"h_drk_ri_207_0_0":{"x":"-45","y":"65"},"h_drk_ri_207_1_0":{"x":"-41","y":"59"},"h_drk_ri_207_2_0":{"x":"-37","y":"56"},"h_drk_ri_207_3_0":{"x":"-26","y":"52"},"h_drk_ri_207_4_0":{"x":"-9","y":"56"},"h_drk_ri_207_5_0":{"x":"-7","y":"54"},"h_drk_ri_207_6_0":{"x":"-11","y":"63"},"h_drk_ri_207_7_0":{"x":"-47","y":"40"},"h_crr_ri_206_0_0":{"x":"-45","y":"46"},"h_crr_ri_206_1_0":{"x":"-44","y":"41"},"h_crr_ri_206_2_0":{"x":"-33","y":"36"},"h_crr_ri_206_3_0":{"x":"-24","y":"38"},"h_crr_ri_206_4_0":{"x":"-9","y":"40"},"h_crr_ri_206_5_0":{"x":"-7","y":"43"},"h_crr_ri_206_6_0":{"x":"-47","y":"42"},"h_crr_ri_206_7_0":{"x":"-49","y":"38"},"h_drk_ri_206_0_0":{"x":"-45","y":"65"},"h_drk_ri_206_1_0":{"x":"-41","y":"59"},"h_drk_ri_206_2_0":{"x":"-37","y":"56"},"h_drk_ri_206_3_0":{"x":"-26","y":"52"},"h_drk_ri_206_4_0":{"x":"-9","y":"56"},"h_drk_ri_206_5_0":{"x":"-7","y":"54"},"h_drk_ri_206_6_0":{"x":"-11","y":"63"},"h_drk_ri_206_7_0":{"x":"-47","y":"40"},"h_crr_ri_205_0_0":{"x":"-46","y":"47"},"h_crr_ri_205_1_0":{"x":"-38","y":"40"},"h_crr_ri_205_2_0":{"x":"-28","y":"36"},"h_crr_ri_205_3_0":{"x":"-21","y":"37"},"h_crr_ri_205_4_0":{"x":"-3","y":"42"},"h_crr_ri_205_5_0":{"x":"-7","y":"42"},"h_crr_ri_205_6_0":{"x":"-25","y":"21"},"h_crr_ri_205_7_0":{"x":"-27","y":"21"},"h_crr_ri_204_0_0":{"x":"-46","y":"47"},"h_crr_ri_204_1_0":{"x":"-38","y":"40"},"h_crr_ri_204_2_0":{"x":"-28","y":"36"},"h_crr_ri_204_3_0":{"x":"-21","y":"37"},"h_crr_ri_204_4_0":{"x":"-3","y":"42"},"h_crr_ri_204_5_0":{"x":"-7","y":"42"},"h_crr_ri_204_6_0":{"x":"-25","y":"21"},"h_crr_ri_204_7_0":{"x":"-27","y":"21"},"h_crr_ri_203_0_0":{"x":"-51","y":"47"},"h_crr_ri_203_1_0":{"x":"-44","y":"43"},"h_crr_ri_203_2_0":{"x":"-35","y":"38"},"h_crr_ri_203_4_0":{"x":"-8","y":"43"},"h_crr_ri_203_3_0":{"x":"-25","y":"39"},"h_crr_ri_203_5_0":{"x":"-13","y":"44"},"h_crr_ri_203_6_0":{"x":"-25","y":"21"},"h_crr_ri_203_7_0":{"x":"-27","y":"21"},"h_drk_ri_203_0_0":{"x":"-40","y":"63"},"h_drk_ri_203_1_0":{"x":"-37","y":"55"},"h_drk_ri_203_2_0":{"x":"-37","y":"53"},"h_drk_ri_203_3_0":{"x":"-29","y":"50"},"h_drk_ri_203_4_0":{"x":"-8","y":"54"},"h_drk_ri_203_5_0":{"x":"0","y":"57"},"h_drk_ri_203_6_0":{"x":"-12","y":"66"},"h_drk_ri_203_7_0":{"x":"-39","y":"22"},"h_crr_ri_202_0_0":{"x":"-51","y":"47"},"h_crr_ri_202_1_0":{"x":"-44","y":"43"},"h_crr_ri_202_2_0":{"x":"-35","y":"38"},"h_crr_ri_202_4_0":{"x":"-8","y":"43"},"h_crr_ri_202_3_0":{"x":"-25","y":"39"},"h_crr_ri_202_5_0":{"x":"-13","y":"44"},"h_crr_ri_202_6_0":{"x":"-25","y":"21"},"h_crr_ri_202_7_0":{"x":"-27","y":"21"},"h_drk_ri_202_0_0":{"x":"-40","y":"63"},"h_drk_ri_202_1_0":{"x":"-37","y":"55"},"h_drk_ri_202_2_0":{"x":"-37","y":"53"},"h_drk_ri_202_3_0":{"x":"-29","y":"50"},"h_drk_ri_202_4_0":{"x":"-8","y":"54"},"h_drk_ri_202_5_0":{"x":"0","y":"57"},"h_drk_ri_202_6_0":{"x":"-12","y":"66"},"h_drk_ri_202_7_0":{"x":"-39","y":"22"},"h_crr_ri_201_0_0":{"x":"-48","y":"40"},"h_crr_ri_201_1_0":{"x":"-43","y":"36"},"h_crr_ri_201_2_0":{"x":"-33","y":"29"},"h_crr_ri_201_3_0":{"x":"-24","y":"31"},"h_crr_ri_201_5_0":{"x":"-12","y":"35"},"h_crr_ri_201_4_0":{"x":"-7","y":"34"},"h_crr_ri_201_6_0":{"x":"-25","y":"21"},"h_crr_ri_201_7_0":{"x":"-27","y":"21"},"h_drk_ri_201_0_0":{"x":"-41","y":"57"},"h_drk_ri_201_1_0":{"x":"-41","y":"56"},"h_drk_ri_201_2_0":{"x":"-37","y":"51"},"h_drk_ri_201_3_0":{"x":"-28","y":"49"},"h_drk_ri_201_4_0":{"x":"-15","y":"53"},"h_drk_ri_201_5_0":{"x":"-7","y":"57"},"h_drk_ri_201_6_0":{"x":"-17","y":"60"},"h_drk_ri_201_7_0":{"x":"-36","y":"52"},"h_crr_ri_200_0_0":{"x":"-48","y":"42"},"h_crr_ri_200_1_0":{"x":"-45","y":"37"},"h_crr_ri_200_2_0":{"x":"-33","y":"31"},"h_crr_ri_200_3_0":{"x":"-24","y":"35"},"h_crr_ri_200_4_0":{"x":"-7","y":"38"},"h_crr_ri_200_5_0":{"x":"-11","y":"38"},"h_crr_ri_200_6_0":{"x":"-31","y":"34"},"h_crr_ri_200_7_0":{"x":"-38","y":"32"},"h_drk_ri_200_0_0":{"x":"-39","y":"61"},"h_drk_ri_200_1_0":{"x":"-40","y":"56"},"h_drk_ri_200_2_0":{"x":"-40","y":"55"},"h_drk_ri_200_3_0":{"x":"-27","y":"52"},"h_drk_ri_200_4_0":{"x":"-13","y":"54"},"h_drk_ri_200_5_0":{"x":"-4","y":"57"},"h_drk_ri_200_6_0":{"x":"-13","y":"61"},"h_drk_ri_200_7_0":{"x":"-38","y":"32"},"h_crr_ri_199_0_0":{"x":"-49","y":"45"},"h_crr_ri_199_1_0":{"x":"-43","y":"40"},"h_crr_ri_199_2_0":{"x":"-34","y":"34"},"h_crr_ri_199_3_0":{"x":"-24","y":"37"},"h_crr_ri_199_4_0":{"x":"-8","y":"40"},"h_crr_ri_199_5_0":{"x":"-7","y":"42"},"h_crr_ri_199_6_0":{"x":"-25","y":"21"},"h_crr_ri_199_7_0":{"x":"-27","y":"21"},"h_drk_ri_199_0_0":{"x":"-38","y":"66"},"h_drk_ri_199_1_0":{"x":"-45","y":"60"},"h_drk_ri_199_2_0":{"x":"-35","y":"57"},"h_drk_ri_199_3_0":{"x":"-27","y":"53"},"h_drk_ri_199_4_0":{"x":"28","y":"55"},"h_drk_ri_199_5_0":{"x":"-5","y":"60"},"h_drk_ri_199_6_0":{"x":"-11","y":"64"},"h_drk_ri_199_7_0":{"x":"-29","y":"62"},"h_crr_ri_198_0_0":{"x":"-49","y":"45"},"h_crr_ri_198_1_0":{"x":"-43","y":"40"},"h_crr_ri_198_2_0":{"x":"-34","y":"34"},"h_crr_ri_198_3_0":{"x":"-24","y":"37"},"h_crr_ri_198_4_0":{"x":"-8","y":"40"},"h_crr_ri_198_5_0":{"x":"-7","y":"42"},"h_crr_ri_198_6_0":{"x":"-25","y":"21"},"h_crr_ri_198_7_0":{"x":"-27","y":"21"},"h_drk_ri_198_0_0":{"x":"-38","y":"66"},"h_drk_ri_198_1_0":{"x":"-45","y":"60"},"h_drk_ri_198_2_0":{"x":"-35","y":"57"},"h_drk_ri_198_3_0":{"x":"-27","y":"53"},"h_drk_ri_198_4_0":{"x":"28","y":"55"},"h_drk_ri_198_5_0":{"x":"-5","y":"60"},"h_drk_ri_198_6_0":{"x":"-11","y":"64"},"h_drk_ri_198_7_0":{"x":"-29","y":"62"},"h_crr_ri_197_0_0":{"x":"-49","y":"45"},"h_crr_ri_197_1_0":{"x":"-43","y":"40"},"h_crr_ri_197_2_0":{"x":"-34","y":"34"},"h_crr_ri_197_3_0":{"x":"-24","y":"37"},"h_crr_ri_197_4_0":{"x":"-8","y":"40"},"h_crr_ri_197_5_0":{"x":"-7","y":"42"},"h_crr_ri_197_6_0":{"x":"-25","y":"21"},"h_crr_ri_197_7_0":{"x":"-27","y":"21"},"h_drk_ri_197_0_0":{"x":"-38","y":"66"},"h_drk_ri_197_1_0":{"x":"-45","y":"60"},"h_drk_ri_197_2_0":{"x":"-35","y":"57"},"h_drk_ri_197_3_0":{"x":"-27","y":"53"},"h_drk_ri_197_4_0":{"x":"-7","y":"52"},"h_drk_ri_197_5_0":{"x":"-5","y":"60"},"h_drk_ri_197_6_0":{"x":"-11","y":"64"},"h_drk_ri_197_7_0":{"x":"-29","y":"62"},"h_crr_ri_196_0_0":{"x":"-50","y":"41"},"h_crr_ri_196_1_0":{"x":"-44","y":"36"},"h_crr_ri_196_2_0":{"x":"-34","y":"31"},"h_crr_ri_196_3_0":{"x":"-24","y":"33"},"h_crr_ri_196_4_0":{"x":"-8","y":"37"},"h_crr_ri_196_5_0":{"x":"-14","y":"38"},"h_crr_ri_196_6_0":{"x":"-25","y":"21"},"h_crr_ri_196_7_0":{"x":"-27","y":"21"},"h_drk_ri_196_0_0":{"x":"-42","y":"61"},"h_drk_ri_196_1_0":{"x":"-39","y":"56"},"h_drk_ri_196_2_0":{"x":"-36","y":"53"},"h_drk_ri_196_3_0":{"x":"-27","y":"51"},"h_drk_ri_196_4_0":{"x":"-10","y":"54"},"h_drk_ri_196_5_0":{"x":"-6","y":"54"},"h_drk_ri_196_6_0":{"x":"-25","y":"21"},"h_drk_ri_196_7_0":{"x":"-27","y":"21"},"h_crr_ri_195_0_0":{"x":"-52","y":"55"},"h_crr_ri_195_1_0":{"x":"-43","y":"50"},"h_crr_ri_195_2_0":{"x":"-31","y":"45"},"h_crr_ri_195_3_0":{"x":"-20","y":"47"},"h_crr_ri_195_4_0":{"x":"0","y":"52"},"h_crr_ri_195_5_0":{"x":"-10","y":"53"},"h_crr_ri_195_6_0":{"x":"-25","y":"21"},"h_crr_ri_195_7_0":{"x":"-43","y":"26"},"h_crr_ri_194_0_0":{"x":"-47","y":"40"},"h_crr_ri_194_1_0":{"x":"-40","y":"32"},"h_crr_ri_194_2_0":{"x":"-29","y":"28"},"h_crr_ri_194_3_0":{"x":"-24","y":"39"},"h_crr_ri_194_4_0":{"x":"3","y":"39"},"h_crr_ri_194_5_0":{"x":"2","y":"39"},"h_crr_ri_194_6_0":{"x":"-25","y":"21"},"h_crr_ri_194_7_0":{"x":"-27","y":"21"},"h_drk_ri_194_0_0":{"x":"-40","y":"75"},"h_drk_ri_194_1_0":{"x":"-46","y":"71"},"h_drk_ri_194_2_0":{"x":"-37","y":"64"},"h_drk_ri_194_3_0":{"x":"-26","y":"48"},"h_drk_ri_194_4_0":{"x":"0","y":"69"},"h_drk_ri_194_5_0":{"x":"2","y":"72"},"h_drk_ri_194_6_0":{"x":"-7","y":"78"},"h_drk_ri_194_7_0":{"x":"-36","y":"50"},"h_crr_ri_193_0_0":{"x":"-44","y":"44"},"h_crr_ri_193_1_0":{"x":"-47","y":"35"},"h_crr_ri_193_2_0":{"x":"-32","y":"31"},"h_crr_ri_193_3_0":{"x":"-25","y":"31"},"h_crr_ri_193_4_0":{"x":"-4","y":"34"},"h_crr_ri_193_5_0":{"x":"-14","y":"36"},"h_crr_ri_193_6_0":{"x":"-25","y":"21"},"h_crr_ri_193_7_0":{"x":"-43","y":"26"},"h_drk_ri_193_0_0":{"x":"-40","y":"66"},"h_drk_ri_193_1_0":{"x":"-47","y":"61"},"h_drk_ri_193_2_0":{"x":"-37","y":"58"},"h_drk_ri_193_3_0":{"x":"-26","y":"53"},"h_drk_ri_193_4_0":{"x":"-11","y":"59"},"h_drk_ri_193_5_0":{"x":"-9","y":"63"},"h_drk_ri_193_6_0":{"x":"-9","y":"67"},"h_drk_ri_193_7_0":{"x":"-43","y":"26"},"h_crr_ri_192_0_0":{"x":"-47","y":"40"},"h_crr_ri_192_1_0":{"x":"-41","y":"37"},"h_crr_ri_192_2_0":{"x":"-31","y":"31"},"h_crr_ri_192_3_0":{"x":"-24","y":"33"},"h_crr_ri_192_4_0":{"x":"-3","y":"35"},"h_crr_ri_192_5_0":{"x":"-11","y":"37"},"h_crr_ri_192_6_0":{"x":"-43","y":"32"},"h_crr_ri_192_7_0":{"x":"-43","y":"27"},"h_drk_ri_192_0_0":{"x":"-39","y":"63"},"h_drk_ri_192_1_0":{"x":"-43","y":"58"},"h_drk_ri_192_2_0":{"x":"-39","y":"55"},"h_drk_ri_192_3_0":{"x":"-28","y":"50"},"h_drk_ri_192_4_0":{"x":"-9","y":"58"},"h_drk_ri_192_5_0":{"x":"-5","y":"60"},"h_drk_ri_192_6_0":{"x":"-25","y":"21"},"h_drk_ri_192_7_0":{"x":"-27","y":"21"},"h_crr_ri_191_0_0":{"x":"-48","y":"42"},"h_crr_ri_191_1_0":{"x":"-42","y":"38"},"h_crr_ri_191_2_0":{"x":"-30","y":"33"},"h_crr_ri_191_3_0":{"x":"-18","y":"36"},"h_crr_ri_191_4_0":{"x":"-3","y":"40"},"h_crr_ri_191_5_0":{"x":"-12","y":"41"},"h_crr_ri_191_6_0":{"x":"-25","y":"21"},"h_crr_ri_191_7_0":{"x":"-27","y":"21"},"h_drk_ri_191_0_0":{"x":"-39","y":"60"},"h_drk_ri_191_1_0":{"x":"-38","y":"59"},"h_drk_ri_191_2_0":{"x":"-35","y":"54"},"h_drk_ri_191_3_0":{"x":"-25","y":"51"},"h_drk_ri_191_4_0":{"x":"-6","y":"57"},"h_drk_ri_191_5_0":{"x":"0","y":"60"},"h_drk_ri_191_6_0":{"x":"-9","y":"62"},"h_drk_ri_191_7_0":{"x":"-35","y":"58"},"h_crr_ri_190_0_0":{"x":"-48","y":"46"},"h_crr_ri_190_1_0":{"x":"-42","y":"38"},"h_crr_ri_190_2_0":{"x":"-32","y":"32"},"h_crr_ri_190_3_0":{"x":"-25","y":"36"},"h_crr_ri_190_4_0":{"x":"-8","y":"39"},"h_crr_ri_190_5_0":{"x":"-11","y":"39"},"h_crr_ri_190_6_0":{"x":"-25","y":"21"},"h_crr_ri_190_7_0":{"x":"-27","y":"21"},"h_drk_ri_190_0_0":{"x":"-41","y":"61"},"h_drk_ri_190_1_0":{"x":"-41","y":"57"},"h_drk_ri_190_2_0":{"x":"-36","y":"55"},"h_drk_ri_190_3_0":{"x":"-29","y":"49"},"h_drk_ri_190_4_0":{"x":"-6","y":"54"},"h_drk_ri_190_5_0":{"x":"-5","y":"57"},"h_drk_ri_190_6_0":{"x":"-11","y":"66"},"h_drk_ri_190_7_0":{"x":"-36","y":"50"},"h_crr_ri_189_0_0":{"x":"-48","y":"45"},"h_crr_ri_189_1_0":{"x":"-44","y":"40"},"h_crr_ri_189_2_0":{"x":"-32","y":"34"},"h_crr_ri_189_3_0":{"x":"-23","y":"36"},"h_crr_ri_189_4_0":{"x":"-1","y":"39"},"h_crr_ri_189_5_0":{"x":"-9","y":"40"},"h_crr_ri_189_6_0":{"x":"-25","y":"21"},"h_crr_ri_189_7_0":{"x":"-27","y":"21"},"h_drk_ri_189_1_0":{"x":"-40","y":"62"},"h_drk_ri_189_2_0":{"x":"-37","y":"59"},"h_drk_ri_189_3_0":{"x":"-28","y":"53"},"h_drk_ri_189_4_0":{"x":"-5","y":"62"},"h_drk_ri_189_5_0":{"x":"-1","y":"61"},"h_drk_ri_189_6_0":{"x":"-25","y":"21"},"h_drk_ri_189_7_0":{"x":"-27","y":"21"},"h_drk_ri_189_0_0":{"x":"-38","y":"63"},"h_crr_ri_188_0_0":{"x":"-49","y":"43"},"h_crr_ri_188_1_0":{"x":"-42","y":"38"},"h_crr_ri_188_2_0":{"x":"-32","y":"32"},"h_crr_ri_188_3_0":{"x":"-25","y":"34"},"h_crr_ri_188_4_0":{"x":"-5","y":"37"},"h_crr_ri_188_5_0":{"x":"-10","y":"40"},"h_crr_ri_188_6_0":{"x":"-25","y":"21"},"h_crr_ri_188_7_0":{"x":"-27","y":"21"},"h_drk_ri_188_0_0":{"x":"-39","y":"63"},"h_drk_ri_188_1_0":{"x":"-42","y":"61"},"h_drk_ri_188_2_0":{"x":"-39","y":"55"},"h_drk_ri_188_3_0":{"x":"-28","y":"51"},"h_drk_ri_188_4_0":{"x":"-8","y":"56"},"h_drk_ri_188_5_0":{"x":"-3","y":"59"},"h_drk_ri_188_6_0":{"x":"-25","y":"21"},"h_drk_ri_188_7_0":{"x":"-27","y":"21"},"h_crr_ri_187_0_0":{"x":"-47","y":"42"},"h_crr_ri_187_1_0":{"x":"-42","y":"37"},"h_crr_ri_187_2_0":{"x":"-33","y":"32"},"h_crr_ri_187_3_0":{"x":"-25","y":"33"},"h_crr_ri_187_4_0":{"x":"-6","y":"36"},"h_crr_ri_187_5_0":{"x":"-11","y":"38"},"h_crr_ri_187_6_0":{"x":"-25","y":"21"},"h_crr_ri_187_7_0":{"x":"-27","y":"21"},"h_drk_ri_187_0_0":{"x":"-39","y":"64"},"h_drk_ri_187_1_0":{"x":"-42","y":"58"},"h_drk_ri_187_2_0":{"x":"-39","y":"54"},"h_drk_ri_187_3_0":{"x":"-28","y":"51"},"h_drk_ri_187_4_0":{"x":"-10","y":"58"},"h_drk_ri_187_5_0":{"x":"-5","y":"61"},"h_drk_ri_187_6_0":{"x":"-25","y":"21"},"h_drk_ri_187_7_0":{"x":"-27","y":"21"},"h_crr_ri_186_0_0":{"x":"-47","y":"42"},"h_crr_ri_186_1_0":{"x":"-42","y":"38"},"h_crr_ri_186_2_0":{"x":"-30","y":"34"},"h_crr_ri_186_3_0":{"x":"-23","y":"35"},"h_crr_ri_186_4_0":{"x":"-4","y":"40"},"h_crr_ri_186_5_0":{"x":"-12","y":"39"},"h_crr_ri_186_6_0":{"x":"-25","y":"21"},"h_crr_ri_186_7_0":{"x":"-27","y":"21"},"h_drk_ri_186_0_0":{"x":"-40","y":"59"},"h_drk_ri_186_1_0":{"x":"-41","y":"56"},"h_drk_ri_186_2_0":{"x":"-36","y":"49"},"h_drk_ri_186_3_0":{"x":"-26","y":"53"},"h_drk_ri_186_4_0":{"x":"-11","y":"56"},"h_drk_ri_186_5_0":{"x":"-4","y":"58"},"h_drk_ri_186_6_0":{"x":"-25","y":"21"},"h_drk_ri_186_7_0":{"x":"-27","y":"21"},"h_crr_ri_185_0_0":{"x":"-51","y":"48"},"h_crr_ri_185_1_0":{"x":"-44","y":"43"},"h_crr_ri_185_2_0":{"x":"-35","y":"37"},"h_crr_ri_185_3_0":{"x":"-25","y":"39"},"h_crr_ri_185_4_0":{"x":"-8","y":"43"},"h_crr_ri_185_5_0":{"x":"-11","y":"44"},"h_crr_ri_185_6_0":{"x":"-25","y":"21"},"h_crr_ri_185_7_0":{"x":"-27","y":"21"},"h_drk_ri_185_0_0":{"x":"-36","y":"60"},"h_drk_ri_185_1_0":{"x":"-40","y":"55"},"h_drk_ri_185_2_0":{"x":"-37","y":"53"},"h_drk_ri_185_3_0":{"x":"-29","y":"52"},"h_drk_ri_185_4_0":{"x":"-2","y":"54"},"h_drk_ri_185_5_0":{"x":"4","y":"56"},"h_drk_ri_185_6_0":{"x":"-9","y":"60"},"h_drk_ri_185_7_0":{"x":"-36","y":"50"},"h_crr_ri_184_7_0":{"x":"-43","y":"27"},"h_crr_ri_184_6_0":{"x":"-42","y":"28"},"h_crr_ri_184_5_0":{"x":"-13","y":"37"},"h_crr_ri_184_4_0":{"x":"-6","y":"36"},"h_crr_ri_184_3_0":{"x":"-23","y":"31"},"h_crr_ri_184_2_0":{"x":"-31","y":"31"},"h_crr_ri_184_1_0":{"x":"-42","y":"36"},"h_crr_ri_184_0_0":{"x":"-45","y":"41"},"h_crr_ri_183_0_0":{"x":"-50","y":"44"},"h_crr_ri_183_1_0":{"x":"-44","y":"38"},"h_crr_ri_183_2_0":{"x":"-33","y":"31"},"h_crr_ri_183_3_0":{"x":"-23","y":"34"},"h_crr_ri_183_4_0":{"x":"-8","y":"37"},"h_crr_ri_183_5_0":{"x":"-13","y":"37"},"h_crr_ri_183_6_0":{"x":"-25","y":"21"},"h_crr_ri_183_7_0":{"x":"-27","y":"21"},"h_drk_ri_183_0_0":{"x":"-38","y":"59"},"h_drk_ri_183_1_0":{"x":"-43","y":"57"},"h_drk_ri_183_2_0":{"x":"-38","y":"53"},"h_drk_ri_183_3_0":{"x":"-29","y":"52"},"h_drk_ri_183_4_0":{"x":"-7","y":"56"},"h_drk_ri_183_5_0":{"x":"-7","y":"56"},"h_drk_ri_183_6_0":{"x":"-10","y":"59"},"h_crr_ri_182_0_0":{"x":"-48","y":"47"},"h_crr_ri_182_1_0":{"x":"-42","y":"40"},"h_crr_ri_182_2_0":{"x":"-31","y":"35"},"h_crr_ri_182_3_0":{"x":"-20","y":"37"},"h_crr_ri_182_4_0":{"x":"1","y":"40"},"h_crr_ri_182_5_0":{"x":"-3","y":"41"},"h_crr_ri_182_6_0":{"x":"-25","y":"21"},"h_crr_ri_182_7_0":{"x":"-27","y":"21"},"h_drk_ri_182_0_0":{"x":"-39","y":"66"},"h_drk_ri_182_1_0":{"x":"-43","y":"66"},"h_drk_ri_182_2_0":{"x":"-39","y":"58"},"h_drk_ri_182_3_0":{"x":"-26","y":"53"},"h_drk_ri_182_4_0":{"x":"-9","y":"58"},"h_drk_ri_182_5_0":{"x":"-5","y":"68"},"h_drk_ri_182_6_0":{"x":"-11","y":"73"},"h_drk_ri_182_7_0":{"x":"-25","y":"63"},"h_crr_ri_181_0_0":{"x":"-50","y":"43"},"h_crr_ri_181_1_0":{"x":"-44","y":"42"},"h_crr_ri_181_2_0":{"x":"-33","y":"36"},"h_crr_ri_181_3_0":{"x":"-25","y":"37"},"h_crr_ri_181_4_0":{"x":"-1","y":"42"},"h_crr_ri_181_5_0":{"x":"-8","y":"44"},"h_crr_ri_181_6_0":{"x":"-25","y":"21"},"h_crr_ri_181_7_0":{"x":"-27","y":"21"},"h_drk_ri_181_0_0":{"x":"-39","y":"63"},"h_drk_ri_181_1_0":{"x":"-42","y":"62"},"h_drk_ri_181_2_0":{"x":"-39","y":"52"},"h_drk_ri_181_3_0":{"x":"-29","y":"52"},"h_drk_ri_181_4_0":{"x":"-9","y":"53"},"h_drk_ri_181_5_0":{"x":"-1","y":"62"},"h_drk_ri_181_6_0":{"x":"-13","y":"66"},"h_drk_ri_181_7_0":{"x":"-34","y":"63"},"h_crr_ri_180_0_0":{"x":"-51","y":"44"},"h_crr_ri_180_1_0":{"x":"-45","y":"40"},"h_crr_ri_180_2_0":{"x":"-33","y":"33"},"h_crr_ri_180_3_0":{"x":"-25","y":"32"},"h_crr_ri_180_4_0":{"x":"-1","y":"38"},"h_crr_ri_180_5_0":{"x":"-8","y":"41"},"h_crr_ri_180_6_0":{"x":"-25","y":"21"},"h_crr_ri_180_7_0":{"x":"-27","y":"21"},"h_drk_ri_180_0_0":{"x":"-39","y":"63"},"h_drk_ri_180_1_0":{"x":"-42","y":"61"},"h_drk_ri_180_2_0":{"x":"-40","y":"53"},"h_drk_ri_180_3_0":{"x":"-28","y":"49"},"h_drk_ri_180_4_0":{"x":"-11","y":"53"},"h_drk_ri_180_5_0":{"x":"-5","y":"61"},"h_drk_ri_180_6_0":{"x":"-13","y":"65"},"h_drk_ri_180_7_0":{"x":"-32","y":"62"},"h_crr_ri_179_0_0":{"x":"-51","y":"43"},"h_crr_ri_179_1_0":{"x":"-45","y":"38"},"h_crr_ri_179_2_0":{"x":"-33","y":"30"},"h_crr_ri_179_3_0":{"x":"-25","y":"32"},"h_crr_ri_179_4_0":{"x":"-1","y":"36"},"h_crr_ri_179_5_0":{"x":"-7","y":"39"},"h_crr_ri_179_6_0":{"x":"-25","y":"21"},"h_crr_ri_179_7_0":{"x":"-27","y":"21"},"h_drk_ri_179_0_0":{"x":"-38","y":"62"},"h_drk_ri_179_1_0":{"x":"-41","y":"56"},"h_drk_ri_179_2_0":{"x":"-39","y":"53"},"h_drk_ri_179_3_0":{"x":"-29","y":"50"},"h_drk_ri_179_4_0":{"x":"-11","y":"55"},"h_drk_ri_179_5_0":{"x":"-4","y":"57"},"h_drk_ri_179_6_0":{"x":"-12","y":"61"},"h_drk_ri_179_7_0":{"x":"-32","y":"61"},"h_crr_ri_178_0_0":{"x":"-46","y":"46"},"h_crr_ri_178_1_0":{"x":"-42","y":"40"},"h_crr_ri_178_2_0":{"x":"-32","y":"35"},"h_crr_ri_178_3_0":{"x":"-23","y":"35"},"h_crr_ri_178_4_0":{"x":"-7","y":"38"},"h_crr_ri_178_5_0":{"x":"-5","y":"40"},"h_crr_ri_178_6_0":{"x":"-25","y":"21"},"h_crr_ri_178_7_0":{"x":"-27","y":"21"},"h_drk_ri_178_0_0":{"x":"-38","y":"64"},"h_drk_ri_178_1_0":{"x":"-42","y":"61"},"h_drk_ri_178_2_0":{"x":"-36","y":"56"},"h_drk_ri_178_3_0":{"x":"-26","y":"56"},"h_drk_ri_178_4_0":{"x":"-10","y":"58"},"h_drk_ri_178_5_0":{"x":"-6","y":"60"},"h_drk_ri_178_6_0":{"x":"-17","y":"63"},"h_drk_ri_178_7_0":{"x":"-32","y":"63"},"h_crr_ri_177_0_0":{"x":"-44","y":"50"},"h_crr_ri_177_1_0":{"x":"-41","y":"46"},"h_crr_ri_177_2_0":{"x":"-32","y":"42"},"h_crr_ri_177_3_0":{"x":"-24","y":"43"},"h_crr_ri_177_4_0":{"x":"-8","y":"44"},"h_crr_ri_177_5_0":{"x":"-10","y":"49"},"h_crr_ri_177_6_0":{"x":"-38","y":"34"},"h_crr_ri_177_7_0":{"x":"-40","y":"33"},"h_crr_ri_176_0_0":{"x":"-44","y":"50"},"h_crr_ri_176_1_0":{"x":"-41","y":"46"},"h_crr_ri_176_2_0":{"x":"-32","y":"42"},"h_crr_ri_176_3_0":{"x":"-24","y":"43"},"h_crr_ri_176_4_0":{"x":"-8","y":"44"},"h_crr_ri_176_5_0":{"x":"-10","y":"49"},"h_crr_ri_176_6_0":{"x":"-38","y":"34"},"h_crr_ri_176_7_0":{"x":"-40","y":"33"},"h_crr_ri_175_0_0":{"x":"-44","y":"47"},"h_crr_ri_175_1_0":{"x":"-41","y":"44"},"h_crr_ri_175_2_0":{"x":"-32","y":"40"},"h_crr_ri_175_3_0":{"x":"-24","y":"41"},"h_crr_ri_175_4_0":{"x":"-8","y":"42"},"h_crr_ri_175_5_0":{"x":"-10","y":"47"},"h_crr_ri_175_6_0":{"x":"-38","y":"34"},"h_crr_ri_175_7_0":{"x":"-40","y":"33"},"h_crr_ri_174_0_0":{"x":"-44","y":"46"},"h_crr_ri_174_1_0":{"x":"-39","y":"42"},"h_crr_ri_174_2_0":{"x":"-32","y":"38"},"h_crr_ri_174_3_0":{"x":"-24","y":"41"},"h_crr_ri_174_4_0":{"x":"-8","y":"42"},"h_crr_ri_174_5_0":{"x":"-11","y":"45"},"h_crr_ri_174_6_0":{"x":"-38","y":"34"},"h_crr_ri_174_7_0":{"x":"-40","y":"33"},"h_crr_ri_173_0_0":{"x":"-46","y":"54"},"h_crr_ri_173_1_0":{"x":"-46","y":"41"},"h_crr_ri_173_2_0":{"x":"-36","y":"41"},"h_crr_ri_173_4_0":{"x":"1","y":"46"},"h_crr_ri_173_3_0":{"x":"-25","y":"122"},"h_crr_ri_173_7_0":{"x":"-26","y":"19"},"h_crr_ri_173_5_0":{"x":"-5","y":"41"},"h_crr_ri_173_6_0":{"x":"-26","y":"21"},"h_crr_ri_172_2_0":{"x":"-33","y":"39"},"h_crr_ri_172_4_0":{"x":"-4","y":"39"},"h_crr_ri_172_5_0":{"x":"-11","y":"41"},"h_crr_ri_172_1_0":{"x":"-41","y":"41"},"h_crr_ri_172_6_0":{"x":"-15","y":"49"},"h_crr_ri_172_7_0":{"x":"-34","y":"39"},"h_crr_ri_172_3_0":{"x":"-25","y":"38"},"h_crr_ri_172_0_0":{"x":"-36","y":"52"},"h_crr_ri_171_0_0":{"x":"-48","y":"44"},"h_crr_ri_171_1_0":{"x":"-43","y":"41"},"h_crr_ri_171_2_0":{"x":"-31","y":"36"},"h_crr_ri_171_3_0":{"x":"-23","y":"36"},"h_crr_ri_171_4_0":{"x":"-4","y":"42"},"h_crr_ri_171_5_0":{"x":"-13","y":"43"},"h_crr_ri_171_6_0":{"x":"-25","y":"21"},"h_crr_ri_171_7_0":{"x":"-27","y":"21"},"h_drk_ri_171_0_0":{"x":"-36","y":"60"},"h_drk_ri_171_1_0":{"x":"-39","y":"58"},"h_drk_ri_171_2_0":{"x":"-34","y":"53"},"h_drk_ri_171_3_0":{"x":"-30","y":"53"},"h_drk_ri_171_4_0":{"x":"-9","y":"55"},"h_drk_ri_171_5_0":{"x":"-2","y":"58"},"h_drk_ri_171_6_0":{"x":"-14","y":"64"},"h_drk_ri_171_7_0":{"x":"-33","y":"61"},"h_crr_ri_170_0_0":{"x":"-48","y":"44"},"h_crr_ri_170_1_0":{"x":"-43","y":"41"},"h_crr_ri_170_2_0":{"x":"-31","y":"36"},"h_crr_ri_170_3_0":{"x":"-23","y":"36"},"h_crr_ri_170_4_0":{"x":"-4","y":"42"},"h_crr_ri_170_5_0":{"x":"-13","y":"43"},"h_crr_ri_170_6_0":{"x":"-25","y":"21"},"h_crr_ri_170_7_0":{"x":"-27","y":"21"},"h_drk_ri_170_0_0":{"x":"-36","y":"60"},"h_drk_ri_170_1_0":{"x":"-39","y":"58"},"h_drk_ri_170_2_0":{"x":"-34","y":"53"},"h_drk_ri_170_3_0":{"x":"-30","y":"53"},"h_drk_ri_170_4_0":{"x":"-9","y":"55"},"h_drk_ri_170_5_0":{"x":"-2","y":"58"},"h_drk_ri_170_6_0":{"x":"-14","y":"64"},"h_drk_ri_170_7_0":{"x":"-33","y":"61"},"h_crr_ri_169_0_0":{"x":"-52","y":"43"},"h_crr_ri_169_1_0":{"x":"-45","y":"39"},"h_crr_ri_169_2_0":{"x":"-35","y":"33"},"h_crr_ri_169_3_0":{"x":"-26","y":"35"},"h_crr_ri_169_4_0":{"x":"-8","y":"38"},"h_crr_ri_169_5_0":{"x":"-12","y":"39"},"h_crr_ri_169_6_0":{"x":"-25","y":"21"},"h_crr_ri_169_7_0":{"x":"-27","y":"21"},"h_drk_ri_169_0_0":{"x":"-41","y":"64"},"h_drk_ri_169_1_0":{"x":"-40","y":"61"},"h_drk_ri_169_2_0":{"x":"-36","y":"55"},"h_drk_ri_169_3_0":{"x":"-27","y":"52"},"h_drk_ri_169_4_0":{"x":"-9","y":"59"},"h_drk_ri_169_6_0":{"x":"-13","y":"65"},"h_drk_ri_169_5_0":{"x":"-3","y":"62"},"h_drk_ri_169_7_0":{"x":"-33","y":"62"},"h_crr_ri_168_0_0":{"x":"-52","y":"43"},"h_crr_ri_168_1_0":{"x":"-45","y":"39"},"h_crr_ri_168_2_0":{"x":"-35","y":"33"},"h_crr_ri_168_3_0":{"x":"-26","y":"35"},"h_crr_ri_168_4_0":{"x":"-8","y":"38"},"h_crr_ri_168_5_0":{"x":"-12","y":"39"},"h_crr_ri_168_6_0":{"x":"-25","y":"21"},"h_crr_ri_168_7_0":{"x":"-27","y":"21"},"h_drk_ri_168_0_0":{"x":"-41","y":"64"},"h_drk_ri_168_1_0":{"x":"-40","y":"61"},"h_drk_ri_168_2_0":{"x":"-36","y":"55"},"h_drk_ri_168_3_0":{"x":"-27","y":"52"},"h_drk_ri_168_4_0":{"x":"-9","y":"59"},"h_drk_ri_168_6_0":{"x":"-13","y":"65"},"h_drk_ri_168_5_0":{"x":"-3","y":"62"},"h_drk_ri_168_7_0":{"x":"-33","y":"62"},"h_crr_ri_167_6_0":{"x":"-25","y":"21"},"h_crr_ri_167_7_0":{"x":"-27","y":"21"},"h_crr_ri_167_5_0":{"x":"-7","y":"38"},"h_crr_ri_167_3_0":{"x":"-23","y":"35"},"h_crr_ri_167_4_0":{"x":"0","y":"35"},"h_crr_ri_167_2_0":{"x":"-34","y":"30"},"h_crr_ri_167_1_0":{"x":"-45","y":"36"},"h_crr_ri_167_0_0":{"x":"-51","y":"42"},"h_crr_ri_166_6_0":{"x":"-25","y":"21"},"h_crr_ri_166_7_0":{"x":"-27","y":"21"},"h_crr_ri_166_5_0":{"x":"-7","y":"38"},"h_crr_ri_166_3_0":{"x":"-23","y":"35"},"h_crr_ri_166_4_0":{"x":"0","y":"35"},"h_crr_ri_166_2_0":{"x":"-34","y":"30"},"h_crr_ri_166_1_0":{"x":"-45","y":"36"},"h_crr_ri_166_0_0":{"x":"-51","y":"42"},"h_crr_ri_165_6_0":{"x":"-25","y":"21"},"h_crr_ri_165_7_0":{"x":"-27","y":"21"},"h_crr_ri_165_5_0":{"x":"-7","y":"38"},"h_crr_ri_165_3_0":{"x":"-23","y":"35"},"h_crr_ri_165_4_0":{"x":"0","y":"35"},"h_crr_ri_165_2_0":{"x":"-34","y":"30"},"h_crr_ri_165_1_0":{"x":"-45","y":"36"},"h_crr_ri_165_0_0":{"x":"-51","y":"42"},"h_crr_ri_164_0_0":{"x":"-51","y":"41"},"h_crr_ri_164_1_0":{"x":"-45","y":"36"},"h_crr_ri_164_2_0":{"x":"-35","y":"30"},"h_crr_ri_164_3_0":{"x":"-25","y":"32"},"h_crr_ri_164_4_0":{"x":"-7","y":"36"},"h_crr_ri_164_5_0":{"x":"-10","y":"36"},"h_crr_ri_164_6_0":{"x":"-25","y":"21"},"h_crr_ri_164_7_0":{"x":"-27","y":"21"},"h_drk_ri_164_0_0":{"x":"-42","y":"59"},"h_drk_ri_164_1_0":{"x":"-43","y":"56"},"h_drk_ri_164_2_0":{"x":"-39","y":"52"},"h_drk_ri_164_3_0":{"x":"-28","y":"51"},"h_drk_ri_164_4_0":{"x":"-13","y":"53"},"h_drk_ri_164_5_0":{"x":"-3","y":"58"},"h_drk_ri_164_6_0":{"x":"-14","y":"61"},"h_drk_ri_164_7_0":{"x":"-39","y":"47"},"h_crr_ri_163_6_0":{"x":"-25","y":"21"},"h_crr_ri_163_5_0":{"x":"-15","y":"45"},"h_crr_ri_163_7_0":{"x":"-27","y":"21"},"h_crr_ri_163_3_0":{"x":"-23","y":"43"},"h_crr_ri_163_4_0":{"x":"-5","y":"46"},"h_crr_ri_163_2_0":{"x":"-33","y":"42"},"h_crr_ri_163_1_0":{"x":"-41","y":"46"},"h_crr_ri_163_0_0":{"x":"-46","y":"50"},"h_crr_ri_162_0_0":{"x":"-48","y":"50"},"h_crr_ri_162_1_0":{"x":"-43","y":"44"},"h_crr_ri_162_2_0":{"x":"-32","y":"41"},"h_crr_ri_162_4_0":{"x":"-5","y":"41"},"h_crr_ri_162_3_0":{"x":"-23","y":"40"},"h_crr_ri_162_7_0":{"x":"-27","y":"21"},"h_crr_ri_162_5_0":{"x":"-12","y":"44"},"h_crr_ri_162_6_0":{"x":"-25","y":"21"},"h_crr_ri_161_0_0":{"x":"-46","y":"49"},"h_crr_ri_161_1_0":{"x":"-41","y":"44"},"h_crr_ri_161_2_0":{"x":"-31","y":"40"},"h_crr_ri_161_4_0":{"x":"-6","y":"41"},"h_crr_ri_161_3_0":{"x":"-21","y":"41"},"h_crr_ri_161_7_0":{"x":"-27","y":"21"},"h_crr_ri_161_5_0":{"x":"-14","y":"42"},"h_crr_ri_161_6_0":{"x":"-25","y":"21"},"h_crr_ri_160_0_0":{"x":"-47","y":"46"},"h_crr_ri_160_1_0":{"x":"-40","y":"42"},"h_crr_ri_160_2_0":{"x":"-31","y":"37"},"h_crr_ri_160_3_0":{"x":"-21","y":"40"},"h_crr_ri_160_4_0":{"x":"-3","y":"42"},"h_crr_ri_160_5_0":{"x":"-9","y":"41"},"h_crr_ri_160_6_0":{"x":"-25","y":"21"},"h_crr_ri_160_7_0":{"x":"-27","y":"21"},"h_drk_ri_160_0_0":{"x":"-36","y":"62"},"h_drk_ri_160_1_0":{"x":"-43","y":"59"},"h_drk_ri_160_2_0":{"x":"-35","y":"57"},"h_drk_ri_160_3_0":{"x":"-25","y":"55"},"h_drk_ri_160_4_0":{"x":"-7","y":"59"},"h_drk_ri_160_5_0":{"x":"-3","y":"61"},"h_drk_ri_160_6_0":{"x":"-8","y":"62"},"h_drk_ri_160_7_0":{"x":"-29","y":"65"},"h_crr_ri_159_0_0":{"x":"-48","y":"47"},"h_crr_ri_159_1_0":{"x":"-41","y":"40"},"h_crr_ri_159_2_0":{"x":"-33","y":"37"},"h_crr_ri_159_3_0":{"x":"-24","y":"38"},"h_crr_ri_159_4_0":{"x":"-7","y":"41"},"h_crr_ri_159_5_0":{"x":"-10","y":"41"},"h_crr_ri_159_6_0":{"x":"-25","y":"21"},"h_crr_ri_159_7_0":{"x":"-27","y":"21"},"h_drk_ri_159_0_0":{"x":"-38","y":"63"},"h_drk_ri_159_1_0":{"x":"-43","y":"59"},"h_drk_ri_159_2_0":{"x":"-37","y":"55"},"h_drk_ri_159_3_0":{"x":"-27","y":"55"},"h_drk_ri_159_4_0":{"x":"-9","y":"55"},"h_drk_ri_159_5_0":{"x":"-6","y":"56"},"h_drk_ri_159_6_0":{"x":"-17","y":"61"},"h_drk_ri_159_7_0":{"x":"-29","y":"61"},"h_crr_ri_158_0_0":{"x":"-49","y":"45"},"h_crr_ri_158_4_0":{"x":"-4","y":"37"},"h_crr_ri_158_2_0":{"x":"-33","y":"34"},"h_crr_ri_158_1_0":{"x":"-43","y":"39"},"h_crr_ri_158_3_0":{"x":"-25","y":"34"},"h_crr_ri_158_5_0":{"x":"-7","y":"37"},"h_crr_ri_158_6_0":{"x":"-25","y":"21"},"h_crr_ri_158_7_0":{"x":"-27","y":"21"},"h_crr_ri_157_0_0":{"x":"-49","y":"45"},"h_crr_ri_157_4_0":{"x":"-4","y":"37"},"h_crr_ri_157_2_0":{"x":"-33","y":"34"},"h_crr_ri_157_1_0":{"x":"-43","y":"39"},"h_crr_ri_157_3_0":{"x":"-25","y":"34"},"h_crr_ri_157_5_0":{"x":"-7","y":"37"},"h_crr_ri_157_6_0":{"x":"-25","y":"21"},"h_crr_ri_157_7_0":{"x":"-27","y":"21"},"h_crr_ri_156_0_0":{"x":"-49","y":"45"},"h_crr_ri_156_4_0":{"x":"-4","y":"37"},"h_crr_ri_156_2_0":{"x":"-33","y":"34"},"h_crr_ri_156_1_0":{"x":"-43","y":"39"},"h_crr_ri_156_3_0":{"x":"-25","y":"34"},"h_crr_ri_156_5_0":{"x":"-7","y":"37"},"h_crr_ri_156_6_0":{"x":"-25","y":"21"},"h_crr_ri_156_7_0":{"x":"-27","y":"21"},"h_crr_ri_155_0_0":{"x":"-47","y":"49"},"h_crr_ri_155_1_0":{"x":"-41","y":"45"},"h_crr_ri_155_2_0":{"x":"-31","y":"40"},"h_crr_ri_155_3_0":{"x":"-21","y":"43"},"h_crr_ri_155_4_0":{"x":"-3","y":"46"},"h_crr_ri_155_5_0":{"x":"-11","y":"48"},"h_crr_ri_155_6_0":{"x":"-25","y":"21"},"h_crr_ri_155_7_0":{"x":"-41","y":"48"},"h_crr_ri_154_0_0":{"x":"-53","y":"40"},"h_crr_ri_154_1_0":{"x":"-46","y":"34"},"h_crr_ri_154_2_0":{"x":"-35","y":"28"},"h_crr_ri_154_3_0":{"x":"-27","y":"30"},"h_crr_ri_154_4_0":{"x":"-5","y":"36"},"h_crr_ri_154_5_0":{"x":"-8","y":"37"},"h_crr_ri_154_6_0":{"x":"-37","y":"33"},"h_crr_ri_154_7_0":{"x":"-37","y":"31"},"h_crr_ri_153_0_0":{"x":"-49","y":"40"},"h_crr_ri_153_1_0":{"x":"-43","y":"35"},"h_crr_ri_153_2_0":{"x":"-32","y":"30"},"h_crr_ri_153_3_0":{"x":"-22","y":"33"},"h_crr_ri_153_4_0":{"x":"-3","y":"35"},"h_crr_ri_153_5_0":{"x":"-10","y":"39"},"h_crr_ri_153_6_0":{"x":"-25","y":"21"},"h_crr_ri_153_7_0":{"x":"-27","y":"21"},"h_drk_ri_153_0_0":{"x":"-42","y":"70"},"h_drk_ri_153_1_0":{"x":"-43","y":"57"},"h_drk_ri_153_2_0":{"x":"-39","y":"52"},"h_drk_ri_153_3_0":{"x":"-28","y":"49"},"h_drk_ri_153_4_0":{"x":"-4","y":"54"},"h_drk_ri_153_5_0":{"x":"1","y":"57"},"h_drk_ri_153_6_0":{"x":"-8","y":"60"},"h_drk_ri_153_7_0":{"x":"-32","y":"65"},"h_drk_ri_152_0_0":{"x":"-41","y":"62"},"h_drk_ri_152_1_0":{"x":"-41","y":"60"},"h_drk_ri_152_2_0":{"x":"-37","y":"57"},"h_drk_ri_152_3_0":{"x":"-26","y":"53"},"h_drk_ri_152_4_0":{"x":"-3","y":"57"},"h_drk_ri_152_5_0":{"x":"-3","y":"60"},"h_drk_ri_152_6_0":{"x":"-11","y":"62"},"h_drk_ri_152_7_0":{"x":"-23","y":"29"},"h_crr_ri_152_0_0":{"x":"-52","y":"45"},"h_crr_ri_152_1_0":{"x":"-46","y":"39"},"h_crr_ri_152_2_0":{"x":"-35","y":"31"},"h_crr_ri_152_3_0":{"x":"-26","y":"34"},"h_crr_ri_152_4_0":{"x":"-2","y":"38"},"h_crr_ri_152_5_0":{"x":"-6","y":"40"},"h_crr_ri_152_6_0":{"x":"-22","y":"29"},"h_crr_ri_152_7_0":{"x":"-23","y":"29"},"h_crr_ri_151_0_0":{"x":"-48","y":"32"},"h_crr_ri_151_1_0":{"x":"-41","y":"24"},"h_crr_ri_151_2_0":{"x":"-29","y":"23"},"h_crr_ri_151_3_0":{"x":"-21","y":"27"},"h_crr_ri_151_4_0":{"x":"-3","y":"30"},"h_crr_ri_151_5_0":{"x":"-10","y":"30"},"h_crr_ri_151_6_0":{"x":"-32","y":"48"},"h_crr_ri_151_7_0":{"x":"-41","y":"27"},"h_crr_ri_150_0_0":{"x":"-36","y":"86"},"h_crr_ri_150_1_0":{"x":"-33","y":"86"},"h_crr_ri_150_2_0":{"x":"-23","y":"83"},"h_crr_ri_150_3_0":{"x":"-14","y":"81"},"h_crr_ri_150_4_0":{"x":"1","y":"86"},"h_crr_ri_150_5_0":{"x":"-5","y":"81"},"h_crr_ri_150_6_0":{"x":"-20","y":"81"},"h_crr_ri_150_7_0":{"x":"-8","y":"81"},"h_crr_ri_149_0_0":{"x":"-36","y":"86"},"h_crr_ri_149_1_0":{"x":"-33","y":"86"},"h_crr_ri_149_2_0":{"x":"-23","y":"83"},"h_crr_ri_149_3_0":{"x":"-14","y":"81"},"h_crr_ri_149_4_0":{"x":"1","y":"86"},"h_crr_ri_149_5_0":{"x":"-5","y":"81"},"h_crr_ri_149_6_0":{"x":"-20","y":"81"},"h_crr_ri_149_7_0":{"x":"-8","y":"81"},"h_crr_ri_148_0_0":{"x":"-36","y":"86"},"h_crr_ri_148_1_0":{"x":"-33","y":"86"},"h_crr_ri_148_2_0":{"x":"-23","y":"83"},"h_crr_ri_148_3_0":{"x":"-14","y":"81"},"h_crr_ri_148_4_0":{"x":"1","y":"86"},"h_crr_ri_148_5_0":{"x":"-5","y":"81"},"h_crr_ri_148_6_0":{"x":"-20","y":"81"},"h_crr_ri_148_7_0":{"x":"-8","y":"81"},"h_crr_ri_147_0_0":{"x":"-36","y":"86"},"h_crr_ri_147_1_0":{"x":"-33","y":"86"},"h_crr_ri_147_2_0":{"x":"-23","y":"83"},"h_crr_ri_147_3_0":{"x":"-14","y":"81"},"h_crr_ri_147_4_0":{"x":"1","y":"86"},"h_crr_ri_147_5_0":{"x":"-5","y":"81"},"h_crr_ri_147_6_0":{"x":"-20","y":"81"},"h_crr_ri_147_7_0":{"x":"-8","y":"81"},"h_crr_ri_146_0_0":{"x":"-48","y":"43"},"h_crr_ri_146_1_0":{"x":"-42","y":"39"},"h_crr_ri_146_2_0":{"x":"-31","y":"34"},"h_crr_ri_146_3_0":{"x":"-23","y":"36"},"h_crr_ri_146_4_0":{"x":"-4","y":"39"},"h_crr_ri_146_5_0":{"x":"-9","y":"41"},"h_crr_ri_146_6_0":{"x":"-42","y":"27"},"h_crr_ri_146_7_0":{"x":"-44","y":"26"},"h_crr_ri_145_0_0":{"x":"-51","y":"49"},"h_crr_ri_145_1_0":{"x":"-45","y":"45"},"h_drk_ri_145_2_0":{"x":"-38","y":"54"},"h_drk_ri_145_3_0":{"x":"-28","y":"50"},"h_drk_ri_145_4_0":{"x":"-3","y":"56"},"h_crr_ri_145_5_0":{"x":"-10","y":"46"},"h_crr_ri_145_6_0":{"x":"-6","y":"61"},"h_drk_ri_145_7_0":{"x":"-23","y":"21"},"h_crr_ri_145_2_0":{"x":"-34","y":"39"},"h_crr_ri_145_3_0":{"x":"-24","y":"42"},"h_crr_ri_145_4_0":{"x":"-6","y":"44"},"h_drk_ri_145_6_0":{"x":"-22","y":"21"},"h_drk_ri_144_0_0":{"x":"-40","y":"61"},"h_drk_ri_144_1_0":{"x":"-40","y":"56"},"h_drk_ri_144_2_0":{"x":"-37","y":"54"},"h_drk_ri_144_3_0":{"x":"-28","y":"50"},"h_drk_ri_144_4_0":{"x":"-8","y":"55"},"h_drk_ri_144_5_0":{"x":"-2","y":"59"},"h_drk_ri_144_6_0":{"x":"-13","y":"60"},"h_drk_ri_144_7_0":{"x":"-41","y":"49"},"h_crr_ri_144_0_0":{"x":"-51","y":"45"},"h_crr_ri_144_1_0":{"x":"-45","y":"41"},"h_crr_ri_144_2_0":{"x":"-34","y":"35"},"h_crr_ri_144_3_0":{"x":"-24","y":"39"},"h_crr_ri_144_4_0":{"x":"-6","y":"40"},"h_crr_ri_144_5_0":{"x":"-10","y":"42"},"h_crr_ri_144_6_0":{"x":"-22","y":"21"},"h_crr_ri_144_7_0":{"x":"-23","y":"21"},"h_crr_ri_143_0_0":{"x":"-53","y":"49"},"h_crr_ri_143_1_0":{"x":"-47","y":"43"},"h_crr_ri_143_2_0":{"x":"-35","y":"38"},"h_crr_ri_143_3_0":{"x":"-28","y":"40"},"h_crr_ri_143_4_0":{"x":"1","y":"44"},"h_crr_ri_143_5_0":{"x":"-7","y":"44"},"h_crr_ri_143_6_0":{"x":"-25","y":"21"},"h_crr_ri_143_7_0":{"x":"-27","y":"21"},"h_crr_ri_110_2_0":{"x":"-33","y":"39"},"h_crr_ri_110_4_0":{"x":"-4","y":"39"},"h_crr_ri_110_5_0":{"x":"-11","y":"41"},"h_crr_ri_110_1_0":{"x":"-41","y":"41"},"h_crr_ri_110_6_0":{"x":"-15","y":"49"},"h_crr_ri_110_7_0":{"x":"-34","y":"39"},"h_crr_ri_110_3_0":{"x":"-25","y":"38"},"h_crr_ri_110_0_0":{"x":"-36","y":"52"},"h_crr_ri_141_0_0":{"x":"-44","y":"46"},"h_crr_ri_141_1_0":{"x":"-39","y":"42"},"h_crr_ri_141_2_0":{"x":"-32","y":"38"},"h_crr_ri_141_3_0":{"x":"-24","y":"41"},"h_crr_ri_141_4_0":{"x":"-8","y":"42"},"h_crr_ri_141_5_0":{"x":"-11","y":"45"},"h_crr_ri_141_6_0":{"x":"-38","y":"34"},"h_crr_ri_141_7_0":{"x":"-40","y":"33"},"h_crr_ri_140_0_0":{"x":"-47","y":"51"},"h_crr_ri_140_1_0":{"x":"-41","y":"44"},"h_crr_ri_140_2_0":{"x":"-29","y":"42"},"h_crr_ri_140_3_0":{"x":"-25","y":"42"},"h_crr_ri_140_4_0":{"x":"-1","y":"48"},"h_crr_ri_140_5_0":{"x":"-10","y":"46"},"h_crr_ri_140_6_0":{"x":"-25","y":"21"},"h_crr_ri_140_7_0":{"x":"-27","y":"21"},"h_crr_ri_139_0_0":{"x":"-50","y":"45"},"h_crr_ri_139_1_0":{"x":"-46","y":"39"},"h_crr_ri_139_2_0":{"x":"-35","y":"35"},"h_crr_ri_139_3_0":{"x":"-26","y":"36"},"h_crr_ri_139_4_0":{"x":"-8","y":"38"},"h_crr_ri_139_5_0":{"x":"-14","y":"42"},"h_crr_ri_139_6_0":{"x":"-34","y":"61"},"h_crr_ri_139_7_0":{"x":"-33","y":"57"},"h_drk_ri_139_0_0":{"x":"-40","y":"63"},"h_drk_ri_139_1_0":{"x":"-42","y":"57"},"h_drk_ri_139_2_0":{"x":"-39","y":"54"},"h_drk_ri_139_3_0":{"x":"-28","y":"53"},"h_drk_ri_139_4_0":{"x":"-7","y":"54"},"h_drk_ri_139_5_0":{"x":"-7","y":"54"},"h_drk_ri_139_6_0":{"x":"-13","y":"62"},"h_drk_ri_139_7_0":{"x":"-28","y":"64"},"h_crr_ri_138_0_0":{"x":"-53","y":"49"},"h_crr_ri_138_1_0":{"x":"-47","y":"43"},"h_crr_ri_138_2_0":{"x":"-35","y":"38"},"h_crr_ri_138_3_0":{"x":"-28","y":"40"},"h_crr_ri_138_4_0":{"x":"1","y":"44"},"h_crr_ri_138_5_0":{"x":"-7","y":"44"},"h_crr_ri_138_6_0":{"x":"-25","y":"21"},"h_crr_ri_138_7_0":{"x":"-27","y":"21"},"h_crr_ri_137_0_0":{"x":"-46","y":"42"},"h_crr_ri_137_1_0":{"x":"-41","y":"37"},"h_crr_ri_137_2_0":{"x":"-30","y":"32"},"h_crr_ri_137_3_0":{"x":"-24","y":"35"},"h_crr_ri_137_4_0":{"x":"-8","y":"37"},"h_crr_ri_137_5_0":{"x":"-10","y":"39"},"h_crr_ri_137_6_0":{"x":"-25","y":"21"},"h_crr_ri_137_7_0":{"x":"-27","y":"21"},"h_drk_ri_137_0_0":{"x":"-39","y":"63"},"h_drk_ri_137_1_0":{"x":"-41","y":"60"},"h_drk_ri_137_2_0":{"x":"-41","y":"55"},"h_drk_ri_137_3_0":{"x":"-26","y":"53"},"h_drk_ri_137_4_0":{"x":"-12","y":"56"},"h_drk_ri_137_5_0":{"x":"-6","y":"59"},"h_drk_ri_137_6_0":{"x":"-16","y":"62"},"h_drk_ri_137_7_0":{"x":"-26","y":"62"},"h_drk_ri_136_0_0":{"x":"-45","y":"75"},"h_drk_ri_136_1_0":{"x":"-42","y":"61"},"h_drk_ri_136_2_0":{"x":"-35","y":"58"},"h_drk_ri_136_3_0":{"x":"-24","y":"59"},"h_drk_ri_136_4_0":{"x":"10","y":"60"},"h_drk_ri_136_5_0":{"x":"18","y":"61"},"h_drk_ri_136_6_0":{"x":"3","y":"77"},"h_drk_ri_136_7_0":{"x":"-36","y":"62"},"h_crr_ri_136_0_0":{"x":"-50","y":"46"},"h_crr_ri_136_1_0":{"x":"-44","y":"41"},"h_crr_ri_136_2_0":{"x":"-32","y":"38"},"h_crr_ri_136_4_0":{"x":"-6","y":"43"},"h_crr_ri_136_3_0":{"x":"-22","y":"40"},"h_crr_ri_136_5_0":{"x":"-14","y":"44"},"h_crr_ri_136_6_0":{"x":"-40","y":"48"},"h_crr_ri_136_7_0":{"x":"-44","y":"31"},"h_crr_ri_135_6_0":{"x":"-29","y":"40"},"h_crr_ri_135_5_0":{"x":"-9","y":"40"},"h_crr_ri_135_7_0":{"x":"-38","y":"40"},"h_crr_ri_135_3_0":{"x":"-22","y":"39"},"h_crr_ri_135_4_0":{"x":"-5","y":"36"},"h_crr_ri_135_2_0":{"x":"-28","y":"35"},"h_crr_ri_135_1_0":{"x":"-38","y":"38"},"h_crr_ri_135_0_0":{"x":"-44","y":"44"},"h_crr_ri_134_0_0":{"x":"-46","y":"42"},"h_crr_ri_134_1_0":{"x":"-44","y":"36"},"h_crr_ri_134_2_0":{"x":"-32","y":"31"},"h_crr_ri_134_3_0":{"x":"-25","y":"32"},"h_crr_ri_134_4_0":{"x":"-7","y":"37"},"h_crr_ri_134_5_0":{"x":"-11","y":"38"},"h_crr_ri_134_6_0":{"x":"-25","y":"21"},"h_crr_ri_134_7_0":{"x":"-27","y":"21"},"h_drk_ri_134_0_0":{"x":"-41","y":"62"},"h_drk_ri_134_1_0":{"x":"-43","y":"56"},"h_drk_ri_134_2_0":{"x":"-38","y":"52"},"h_drk_ri_134_3_0":{"x":"-29","y":"50"},"h_drk_ri_134_4_0":{"x":"-8","y":"54"},"h_drk_ri_134_5_0":{"x":"-6","y":"56"},"h_drk_ri_134_6_0":{"x":"-9","y":"61"},"h_drk_ri_134_7_0":{"x":"-34","y":"55"},"h_crr_ri_133_0_0":{"x":"-47","y":"51"},"h_crr_ri_133_1_0":{"x":"-41","y":"47"},"h_crr_ri_133_2_0":{"x":"-29","y":"42"},"h_crr_ri_133_3_0":{"x":"-23","y":"44"},"h_crr_ri_133_4_0":{"x":"-2","y":"48"},"h_crr_ri_133_5_0":{"x":"-10","y":"48"},"h_crr_ri_133_6_0":{"x":"-25","y":"21"},"h_crr_ri_133_7_0":{"x":"-27","y":"21"},"h_drk_ri_133_0_0":{"x":"-37","y":"62"},"h_drk_ri_133_1_0":{"x":"-38","y":"59"},"h_drk_ri_133_2_0":{"x":"-33","y":"56"},"h_drk_ri_133_3_0":{"x":"-26","y":"53"},"h_drk_ri_133_4_0":{"x":"-12","y":"58"},"h_drk_ri_133_5_0":{"x":"-4","y":"59"},"h_drk_ri_133_6_0":{"x":"-11","y":"61"},"h_drk_ri_133_7_0":{"x":"-34","y":"55"},"h_crr_ri_132_0_0":{"x":"-47","y":"51"},"h_crr_ri_132_1_0":{"x":"-41","y":"47"},"h_crr_ri_132_2_0":{"x":"-29","y":"42"},"h_crr_ri_132_3_0":{"x":"-24","y":"44"},"h_crr_ri_132_4_0":{"x":"-2","y":"48"},"h_crr_ri_132_5_0":{"x":"-10","y":"48"},"h_crr_ri_132_6_0":{"x":"-25","y":"21"},"h_crr_ri_132_7_0":{"x":"-27","y":"21"},"h_drk_ri_132_0_0":{"x":"-37","y":"62"},"h_drk_ri_132_1_0":{"x":"-38","y":"59"},"h_drk_ri_132_2_0":{"x":"-33","y":"56"},"h_drk_ri_132_3_0":{"x":"-26","y":"53"},"h_drk_ri_132_4_0":{"x":"-12","y":"58"},"h_drk_ri_132_5_0":{"x":"-4","y":"59"},"h_drk_ri_132_6_0":{"x":"-11","y":"61"},"h_drk_ri_132_7_0":{"x":"-34","y":"55"},"h_crr_ri_131_6_0":{"x":"-25","y":"21"},"h_crr_ri_131_7_0":{"x":"-27","y":"21"},"h_crr_ri_131_0_0":{"x":"-46","y":"47"},"h_crr_ri_131_1_0":{"x":"-41","y":"43"},"h_crr_ri_131_2_0":{"x":"-31","y":"37"},"h_crr_ri_131_4_0":{"x":"-8","y":"41"},"h_crr_ri_131_3_0":{"x":"-23","y":"41"},"h_crr_ri_131_5_0":{"x":"-16","y":"43"},"h_crr_ri_130_0_0":{"x":"-50","y":"42"},"h_crr_ri_130_1_0":{"x":"-45","y":"37"},"h_crr_ri_130_2_0":{"x":"-32","y":"32"},"h_crr_ri_130_3_0":{"x":"-24","y":"34"},"h_crr_ri_130_4_0":{"x":"-7","y":"38"},"h_crr_ri_130_5_0":{"x":"-12","y":"39"},"h_crr_ri_130_6_0":{"x":"-25","y":"21"},"h_crr_ri_130_7_0":{"x":"-27","y":"21"},"h_drk_ri_130_0_0":{"x":"-40","y":"60"},"h_drk_ri_130_1_0":{"x":"-43","y":"56"},"h_drk_ri_130_2_0":{"x":"-36","y":"51"},"h_drk_ri_130_3_0":{"x":"-27","y":"49"},"h_drk_ri_130_4_0":{"x":"-9","y":"53"},"h_drk_ri_130_5_0":{"x":"-4","y":"54"},"h_drk_ri_130_6_0":{"x":"-13","y":"58"},"h_drk_ri_130_7_0":{"x":"-26","y":"59"},"h_crr_ri_129_0_0":{"x":"-50","y":"42"},"h_crr_ri_129_1_0":{"x":"-45","y":"37"},"h_crr_ri_129_2_0":{"x":"-32","y":"32"},"h_crr_ri_129_3_0":{"x":"-24","y":"34"},"h_crr_ri_129_4_0":{"x":"-7","y":"38"},"h_crr_ri_129_5_0":{"x":"-12","y":"39"},"h_crr_ri_129_6_0":{"x":"-25","y":"21"},"h_crr_ri_129_7_0":{"x":"-27","y":"21"},"h_drk_ri_129_0_0":{"x":"-40","y":"60"},"h_drk_ri_129_1_0":{"x":"-43","y":"56"},"h_drk_ri_129_2_0":{"x":"-36","y":"51"},"h_drk_ri_129_3_0":{"x":"-27","y":"49"},"h_drk_ri_129_4_0":{"x":"-9","y":"53"},"h_drk_ri_129_5_0":{"x":"-4","y":"54"},"h_drk_ri_129_6_0":{"x":"-13","y":"58"},"h_drk_ri_129_7_0":{"x":"-26","y":"59"},"h_crr_ri_128_0_0":{"x":"-50","y":"42"},"h_crr_ri_128_1_0":{"x":"-45","y":"37"},"h_crr_ri_128_2_0":{"x":"-32","y":"32"},"h_crr_ri_128_3_0":{"x":"-24","y":"34"},"h_crr_ri_128_4_0":{"x":"-7","y":"38"},"h_crr_ri_128_5_0":{"x":"-12","y":"39"},"h_crr_ri_128_6_0":{"x":"-25","y":"21"},"h_crr_ri_128_7_0":{"x":"-27","y":"21"},"h_drk_ri_128_0_0":{"x":"-40","y":"60"},"h_drk_ri_128_1_0":{"x":"-43","y":"56"},"h_drk_ri_128_2_0":{"x":"-36","y":"51"},"h_drk_ri_128_3_0":{"x":"-27","y":"49"},"h_drk_ri_128_4_0":{"x":"-9","y":"53"},"h_drk_ri_128_5_0":{"x":"-4","y":"54"},"h_drk_ri_128_6_0":{"x":"-13","y":"58"},"h_drk_ri_128_7_0":{"x":"-26","y":"59"},"h_crr_ri_127_0_0":{"x":"-50","y":"46"},"h_drk_ri_127_0_0":{"x":"-38","y":"59"},"h_crr_ri_127_1_0":{"x":"-45","y":"43"},"h_drk_ri_127_1_0":{"x":"-43","y":"58"},"h_crr_ri_127_2_0":{"x":"-34","y":"36"},"h_drk_ri_127_2_0":{"x":"-39","y":"54"},"h_crr_ri_127_3_0":{"x":"-25","y":"36"},"h_drk_ri_127_3_0":{"x":"-29","y":"52"},"h_crr_ri_127_4_0":{"x":"-9","y":"40"},"h_drk_ri_127_4_0":{"x":"-7","y":"56"},"h_crr_ri_127_5_0":{"x":"-15","y":"41"},"h_drk_ri_127_5_0":{"x":"-7","y":"57"},"h_drk_ri_127_6_0":{"x":"-10","y":"59"},"h_crr_ri_126_0_0":{"x":"-52","y":"47"},"h_drk_ri_126_0_0":{"x":"-39","y":"62"},"h_crr_ri_126_1_0":{"x":"-46","y":"41"},"h_drk_ri_126_1_0":{"x":"-39","y":"60"},"h_crr_ri_126_2_0":{"x":"-35","y":"33"},"h_drk_ri_126_2_0":{"x":"-34","y":"57"},"h_crr_ri_126_3_0":{"x":"-26","y":"36"},"h_drk_ri_126_3_0":{"x":"-26","y":"56"},"h_crr_ri_126_4_0":{"x":"-2","y":"40"},"h_drk_ri_126_4_0":{"x":"-3","y":"57"},"h_crr_ri_126_5_0":{"x":"-6","y":"42"},"h_drk_ri_126_5_0":{"x":"-3","y":"60"},"h_drk_ri_126_6_0":{"x":"-11","y":"62"},"h_crr_ri_125_0_0":{"x":"-50","y":"44"},"h_crr_ri_125_1_0":{"x":"-45","y":"39"},"h_crr_ri_125_2_0":{"x":"-34","y":"34"},"h_crr_ri_125_3_0":{"x":"-26","y":"34"},"h_crr_ri_125_4_0":{"x":"-5","y":"38"},"h_crr_ri_125_5_0":{"x":"-13","y":"38"},"h_crr_ri_124_0_0":{"x":"-49","y":"38"},"h_crr_ri_124_1_0":{"x":"-42","y":"34"},"h_crr_ri_124_2_0":{"x":"-29","y":"29"},"h_crr_ri_124_3_0":{"x":"-22","y":"31"},"h_crr_ri_124_4_0":{"x":"-3","y":"34"},"h_crr_ri_124_5_0":{"x":"-12","y":"35"},"h_crr_ri_123_0_0":{"x":"-50","y":"43"},"h_crr_ri_123_1_0":{"x":"-44","y":"40"},"h_crr_ri_123_2_0":{"x":"-32","y":"33"},"h_crr_ri_123_3_0":{"x":"-24","y":"34"},"h_crr_ri_123_4_0":{"x":"-6","y":"37"},"h_crr_ri_123_5_0":{"x":"-15","y":"39"},"h_crr_ri_122_0_0":{"x":"-50","y":"42"},"h_crr_ri_122_1_0":{"x":"-45","y":"37"},"h_crr_ri_122_2_0":{"x":"-34","y":"31"},"h_crr_ri_122_3_0":{"x":"-23","y":"33"},"h_crr_ri_122_4_0":{"x":"-5","y":"36"},"h_crr_ri_122_5_0":{"x":"-13","y":"38"},"h_crr_ri_121_0_0":{"x":"-42","y":"41"},"h_crr_ri_121_1_0":{"x":"-35","y":"38"},"h_crr_ri_121_2_0":{"x":"-24","y":"33"},"h_crr_ri_121_3_0":{"x":"-14","y":"34"},"h_crr_ri_121_4_0":{"x":"-4","y":"38"},"h_crr_ri_121_5_0":{"x":"-6","y":"38"},"h_crr_ri_120_0_0":{"x":"-51","y":"45"},"h_crr_ri_120_1_0":{"x":"-45","y":"39"},"h_crr_ri_120_2_0":{"x":"-33","y":"33"},"h_crr_ri_120_3_0":{"x":"-24","y":"36"},"h_crr_ri_120_4_0":{"x":"-7","y":"37"},"h_crr_ri_120_5_0":{"x":"-12","y":"40"},"h_crr_ri_119_0_0":{"x":"-50","y":"44"},"h_crr_ri_119_1_0":{"x":"-44","y":"39"},"h_crr_ri_119_2_0":{"x":"-34","y":"33"},"h_crr_ri_119_3_0":{"x":"-24","y":"36"},"h_crr_ri_119_4_0":{"x":"-7","y":"40"},"h_crr_ri_119_5_0":{"x":"-15","y":"40"},"h_crr_ri_118_4_0":{"x":"0","y":"46"},"h_crr_ri_118_1_0":{"x":"-39","y":"45"},"h_crr_ri_118_5_0":{"x":"-12","y":"48"},"h_crr_ri_118_2_0":{"x":"-28","y":"40"},"h_crr_ri_118_0_0":{"x":"-44","y":"50"},"h_crr_ri_118_3_0":{"x":"-21","y":"41"},"h_crr_ri_118_6_0":{"x":"83","y":"26"},"h_crr_ri_118_7_0":{"x":"-170","y":"27"},"h_crr_ri_117_2_0":{"x":"-27","y":"35"},"h_crr_ri_117_4_0":{"x":"-1","y":"38"},"h_crr_ri_117_1_0":{"x":"-37","y":"39"},"h_crr_ri_117_5_0":{"x":"-5","y":"40"},"h_crr_ri_117_3_0":{"x":"-22","y":"41"},"h_crr_ri_117_0_0":{"x":"-43","y":"43"},"h_crr_ri_117_6_0":{"x":"-42","y":"27"},"h_crr_ri_117_7_0":{"x":"-44","y":"26"},"h_crr_ri_116_4_0":{"x":"-4","y":"39"},"h_crr_ri_116_0_0":{"x":"-48","y":"43"},"h_crr_ri_116_1_0":{"x":"-42","y":"39"},"h_crr_ri_116_5_0":{"x":"-9","y":"41"},"h_crr_ri_116_2_0":{"x":"-31","y":"34"},"h_crr_ri_116_3_0":{"x":"-23","y":"36"},"h_crr_ri_116_67_0":{"x":"-189","y":"-245"},"h_crr_ri_116_6_0":{"x":"-42","y":"27"},"h_crr_ri_115_2_0":{"x":"-31","y":"34"},"h_crr_ri_115_0_0":{"x":"-50","y":"44"},"h_crr_ri_115_4_0":{"x":"-6","y":"40"},"h_crr_ri_115_5_0":{"x":"-15","y":"43"},"h_crr_ri_115_3_0":{"x":"-24","y":"37"},"h_crr_ri_115_6_0":{"x":"-42","y":"27"},"h_crr_ri_115_7_0":{"x":"-44","y":"26"},"h_crr_ri_115_1_0":{"x":"-45","y":"40"},"h_crr_ri_114_2_0":{"x":"-30","y":"36"},"h_crr_ri_114_4_0":{"x":"1","y":"42"},"h_crr_ri_114_1_0":{"x":"-42","y":"40"},"h_crr_ri_114_0_0":{"x":"-49","y":"46"},"h_crr_ri_114_3_0":{"x":"-20","y":"36"},"h_crr_ri_114_5_0":{"x":"-10","y":"43"},"h_crr_ri_114_7_0":{"x":"-35","y":"44"},"h_crr_ri_114_6_0":{"x":"-42","y":"27"},"h_crr_ri_113_6_0":{"x":"-42","y":"27"},"h_crr_ri_113_5_0":{"x":"-10","y":"44"},"h_crr_ri_113_7_0":{"x":"-44","y":"26"},"h_crr_ri_113_4_0":{"x":"-3","y":"40"},"h_crr_ri_113_3_0":{"x":"-23","y":"40"},"h_crr_ri_113_2_0":{"x":"-30","y":"37"},"h_crr_ri_113_1_0":{"x":"-38","y":"43"},"h_crr_ri_113_0_0":{"x":"-43","y":"45"},"h_crr_ri_112_6_0":{"x":"-42","y":"31"},"h_crr_ri_112_5_0":{"x":"-11","y":"43"},"h_crr_ri_112_7_0":{"x":"-44","y":"26"},"h_crr_ri_112_3_0":{"x":"-21","y":"39"},"h_crr_ri_112_4_0":{"x":"-7","y":"41"},"h_crr_ri_112_2_0":{"x":"-29","y":"38"},"h_crr_ri_112_1_0":{"x":"-39","y":"41"},"h_crr_ri_112_0_0":{"x":"-40","y":"45"},"h_crr_ri_111_0_0":{"x":"-43","y":"59"},"h_crr_ri_111_1_0":{"x":"-36","y":"55"},"h_crr_ri_111_2_0":{"x":"-25","y":"49"},"h_crr_ri_111_4_0":{"x":"1","y":"55"},"h_crr_ri_111_3_0":{"x":"-17","y":"51"},"h_crr_ri_111_5_0":{"x":"-6","y":"57"},"h_crr_ri_111_6_0":{"x":"-43","y":"37"},"h_crr_ri_111_7_0":{"x":"-44","y":"39"},"h_crr_ri_142_0_0":{"x":"-51","y":"47"},"h_crr_ri_142_1_0":{"x":"-44","y":"42"},"h_crr_ri_142_2_0":{"x":"-32","y":"36"},"h_crr_ri_142_3_0":{"x":"-24","y":"38"},"h_crr_ri_142_4_0":{"x":"-7","y":"41"},"h_crr_ri_142_5_0":{"x":"-14","y":"42"},"h_crr_ri_142_6_0":{"x":"-43","y":"37"},"h_crr_ri_142_7_0":{"x":"-44","y":"39"},"h_crr_ri_109_0_0":{"x":"-51","y":"38"},"h_crr_ri_109_1_0":{"x":"-44","y":"35"},"h_crr_ri_109_2_0":{"x":"-36","y":"31"},"h_crr_ri_109_3_0":{"x":"-25","y":"34"},"h_crr_ri_109_4_0":{"x":"-9","y":"40"},"h_crr_ri_109_5_0":{"x":"-13","y":"35"},"h_crr_ri_109_6_0":{"x":"-25","y":"21"},"h_crr_ri_109_7_0":{"x":"-27","y":"21"},"h_drk_ri_109_0_0":{"x":"-39","y":"61"},"h_drk_ri_109_1_0":{"x":"-43","y":"55"},"h_drk_ri_109_2_0":{"x":"-38","y":"53"},"h_drk_ri_109_3_0":{"x":"-29","y":"47"},"h_drk_ri_109_5_0":{"x":"-7","y":"55"},"h_drk_ri_109_6_0":{"x":"-22","y":"63"},"h_drk_ri_109_7_0":{"x":"-33","y":"58"},"h_drk_ri_109_4_0":{"x":"-11","y":"53"},"h_crr_ri_107_0_0":{"x":"-44","y":"48"},"h_crr_ri_107_1_0":{"x":"-43","y":"42"},"h_crr_ri_107_2_0":{"x":"-31","y":"37"},"h_crr_ri_107_3_0":{"x":"-24","y":"38"},"h_crr_ri_107_4_0":{"x":"-1","y":"40"},"h_crr_ri_107_5_0":{"x":"-9","y":"42"},"h_crr_ri_107_6_0":{"x":"-36","y":"37"},"h_crr_ri_107_7_0":{"x":"-33","y":"37"},"h_crr_ri_108_0_0":{"x":"-36","y":"86"},"h_crr_ri_108_1_0":{"x":"-33","y":"86"},"h_crr_ri_108_2_0":{"x":"-23","y":"83"},"h_crr_ri_108_4_0":{"x":"1","y":"86"},"h_crr_ri_108_6_0":{"x":"-20","y":"81"},"h_crr_ri_108_5_0":{"x":"-5","y":"81"},"h_crr_ri_108_7_0":{"x":"-8","y":"81"},"h_crr_ri_108_3_0":{"x":"-14","y":"81"},"h_crr_ri_1_0_0":{"x":"-51","y":"40"},"h_crr_ri_1_1_0":{"x":"-44","y":"35"},"h_crr_ri_1_2_0":{"x":"-36","y":"30"},"h_crr_ri_1_3_0":{"x":"-25","y":"32"},"h_crr_ri_1_4_0":{"x":"-9","y":"36"},"h_crr_ri_1_5_0":{"x":"-13","y":"35"},"h_crr_ri_1_6_0":{"x":"-25","y":"21"},"h_crr_ri_1_7_0":{"x":"-27","y":"21"},"h_drk_ri_1_0_0":{"x":"-40","y":"62"},"h_drk_ri_1_1_0":{"x":"-43","y":"55"},"h_drk_ri_1_2_0":{"x":"-38","y":"53"},"h_drk_ri_1_3_0":{"x":"-29","y":"50"},"h_drk_ri_1_4_0":{"x":"-8","y":"52"},"h_drk_ri_1_5_0":{"x":"-6","y":"54"},"h_drk_ri_1_6_0":{"x":"-17","y":"58"},"h_drk_ri_1_7_0":{"x":"-30","y":"61"},"h_crr_ri_2_0_0":{"x":"-52","y":"52"},"h_crr_ri_2_1_0":{"x":"-46","y":"45"},"h_crr_ri_2_2_0":{"x":"-34","y":"40"},"h_crr_ri_2_3_0":{"x":"-25","y":"42"},"h_crr_ri_2_4_0":{"x":"-9","y":"46"},"h_crr_ri_2_5_0":{"x":"-13","y":"47"},"h_crr_ri_2_6_0":{"x":"-25","y":"21"},"h_crr_ri_2_7_0":{"x":"-27","y":"21"},"h_drk_ri_2_0_0":{"x":"-41","y":"63"},"h_drk_ri_2_1_0":{"x":"-43","y":"55"},"h_drk_ri_2_2_0":{"x":"-37","y":"50"},"h_drk_ri_2_3_0":{"x":"-29","y":"49"},"h_drk_ri_2_4_0":{"x":"-6","y":"52"},"h_drk_ri_2_5_0":{"x":"-4","y":"54"},"h_drk_ri_2_6_0":{"x":"-15","y":"57"},"h_drk_ri_2_7_0":{"x":"-30","y":"62"},"h_crr_ri_3_0_0":{"x":"-50","y":"42"},"h_crr_ri_3_1_0":{"x":"-45","y":"37"},"h_crr_ri_3_2_0":{"x":"-32","y":"32"},"h_crr_ri_3_3_0":{"x":"-24","y":"34"},"h_crr_ri_3_4_0":{"x":"-7","y":"38"},"h_crr_ri_3_5_0":{"x":"-12","y":"39"},"h_crr_ri_3_6_0":{"x":"-25","y":"21"},"h_crr_ri_3_7_0":{"x":"-27","y":"21"},"h_drk_ri_3_0_0":{"x":"-40","y":"60"},"h_drk_ri_3_1_0":{"x":"-43","y":"56"},"h_drk_ri_3_2_0":{"x":"-36","y":"51"},"h_drk_ri_3_3_0":{"x":"-27","y":"49"},"h_drk_ri_3_4_0":{"x":"-9","y":"53"},"h_drk_ri_3_5_0":{"x":"-4","y":"54"},"h_drk_ri_3_6_0":{"x":"-13","y":"58"},"h_drk_ri_3_7_0":{"x":"-26","y":"59"},"h_crr_ri_5_0_0":{"x":"-52","y":"42"},"h_crr_ri_5_1_0":{"x":"-45","y":"38"},"h_crr_ri_5_2_0":{"x":"-35","y":"32"},"h_crr_ri_5_3_0":{"x":"-25","y":"34"},"h_crr_ri_5_4_0":{"x":"-7","y":"38"},"h_crr_ri_5_5_0":{"x":"-11","y":"39"},"h_crr_ri_5_6_0":{"x":"-25","y":"21"},"h_crr_ri_5_7_0":{"x":"-27","y":"21"},"h_drk_ri_5_0_0":{"x":"-38","y":"60"},"h_drk_ri_5_1_0":{"x":"-41","y":"56"},"h_drk_ri_5_2_0":{"x":"-39","y":"51"},"h_drk_ri_5_3_0":{"x":"-29","y":"50"},"h_drk_ri_5_4_0":{"x":"-11","y":"54"},"h_drk_ri_5_5_0":{"x":"-7","y":"56"},"h_drk_ri_5_6_0":{"x":"-17","y":"59"},"h_drk_ri_5_7_0":{"x":"-32","y":"58"},"h_crr_ri_6_0_0":{"x":"-51","y":"42"},"h_crr_ri_6_1_0":{"x":"-46","y":"37"},"h_crr_ri_6_2_0":{"x":"-35","y":"33"},"h_crr_ri_6_3_0":{"x":"-27","y":"32"},"h_crr_ri_6_4_0":{"x":"-7","y":"35"},"h_crr_ri_6_5_0":{"x":"-11","y":"37"},"h_crr_ri_6_6_0":{"x":"-39","y":"49"},"h_crr_ri_6_7_0":{"x":"-39","y":"49"},"h_drk_ri_6_0_0":{"x":"-41","y":"64"},"h_drk_ri_6_1_0":{"x":"-44","y":"57"},"h_drk_ri_6_2_0":{"x":"-39","y":"51"},"h_drk_ri_6_3_0":{"x":"-29","y":"47"},"h_drk_ri_6_4_0":{"x":"-8","y":"55"},"h_drk_ri_6_5_0":{"x":"-6","y":"57"},"h_drk_ri_6_6_0":{"x":"-16","y":"59"},"h_drk_ri_6_7_0":{"x":"-39","y":"49"},"h_crr_ri_9_0_0":{"x":"-52","y":"42"},"h_crr_ri_9_1_0":{"x":"-45","y":"38"},"h_crr_ri_9_2_0":{"x":"-35","y":"32"},"h_crr_ri_9_3_0":{"x":"-25","y":"34"},"h_crr_ri_9_4_0":{"x":"-7","y":"38"},"h_crr_ri_9_5_0":{"x":"-11","y":"39"},"h_crr_ri_9_6_0":{"x":"-25","y":"21"},"h_crr_ri_9_7_0":{"x":"-27","y":"21"},"h_drk_ri_9_0_0":{"x":"-38","y":"60"},"h_drk_ri_9_1_0":{"x":"-41","y":"56"},"h_drk_ri_9_2_0":{"x":"-39","y":"52"},"h_drk_ri_9_3_0":{"x":"-29","y":"50"},"h_drk_ri_9_4_0":{"x":"-11","y":"55"},"h_drk_ri_9_5_0":{"x":"-7","y":"56"},"h_drk_ri_9_6_0":{"x":"-17","y":"59"},"h_drk_ri_9_7_0":{"x":"-32","y":"58"},"h_crr_ri_667_0_0":{"x":"-47","y":"45"},"h_crr_ri_667_1_0":{"x":"-41","y":"40"},"h_crr_ri_667_2_0":{"x":"-30","y":"35"},"h_crr_ri_667_3_0":{"x":"-22","y":"38"},"h_crr_ri_667_4_0":{"x":"-4","y":"40"},"h_crr_ri_667_5_0":{"x":"-9","y":"41"},"h_crr_ri_667_6_0":{"x":"-25","y":"21"},"h_crr_ri_667_7_0":{"x":"-27","y":"21"},"h_drk_ri_667_0_0":{"x":"-40","y":"64"},"h_drk_ri_667_1_0":{"x":"-44","y":"58"},"h_drk_ri_667_2_0":{"x":"-38","y":"52"},"h_drk_ri_667_3_0":{"x":"-26","y":"49"},"h_drk_ri_667_4_0":{"x":"-8","y":"56"},"h_drk_ri_667_5_0":{"x":"-6","y":"59"},"h_drk_ri_667_6_0":{"x":"-16","y":"61"},"h_drk_ri_667_7_0":{"x":"-39","y":"49"},"h_crr_ri_33_0_0":{"x":"-51","y":"42"},"h_crr_ri_33_1_0":{"x":"-46","y":"37"},"h_crr_ri_33_2_0":{"x":"-33","y":"32"},"h_crr_ri_33_3_0":{"x":"-25","y":"34"},"h_crr_ri_33_4_0":{"x":"-8","y":"38"},"h_crr_ri_33_5_0":{"x":"-13","y":"39"},"h_crr_ri_33_6_0":{"x":"-25","y":"21"},"h_crr_ri_33_7_0":{"x":"-27","y":"21"},"h_drk_ri_33_0_0":{"x":"-40","y":"59"},"h_drk_ri_33_1_0":{"x":"-43","y":"55"},"h_drk_ri_33_2_0":{"x":"-36","y":"50"},"h_drk_ri_33_3_0":{"x":"-27","y":"49"},"h_drk_ri_33_4_0":{"x":"-10","y":"53"},"h_drk_ri_33_5_0":{"x":"-5","y":"53"},"h_drk_ri_33_6_0":{"x":"-14","y":"57"},"h_drk_ri_33_7_0":{"x":"-26","y":"58"},"h_crr_ri_42_0_0":{"x":"-51","y":"41"},"h_crr_ri_42_1_0":{"x":"-44","y":"36"},"h_crr_ri_42_2_0":{"x":"-36","y":"31"},"h_crr_ri_42_3_0":{"x":"-25","y":"33"},"h_crr_ri_42_4_0":{"x":"-9","y":"37"},"h_crr_ri_42_5_0":{"x":"-13","y":"36"},"h_crr_ri_42_6_0":{"x":"-25","y":"21"},"h_crr_ri_42_7_0":{"x":"-27","y":"21"},"h_drk_ri_42_0_0":{"x":"-39","y":"63"},"h_drk_ri_42_1_0":{"x":"-43","y":"56"},"h_drk_ri_42_2_0":{"x":"-38","y":"53"},"h_drk_ri_42_3_0":{"x":"-29","y":"50"},"h_drk_ri_42_4_0":{"x":"-11","y":"55"},"h_drk_ri_42_5_0":{"x":"-7","y":"56"},"h_drk_ri_42_6_0":{"x":"-20","y":"65"},"h_drk_ri_42_7_0":{"x":"-33","y":"61"},"h_crr_ri_43_0_0":{"x":"-51","y":"40"},"h_crr_ri_43_1_0":{"x":"-44","y":"35"},"h_crr_ri_43_2_0":{"x":"-36","y":"30"},"h_crr_ri_43_3_0":{"x":"-25","y":"32"},"h_crr_ri_43_4_0":{"x":"-9","y":"36"},"h_crr_ri_43_5_0":{"x":"-13","y":"35"},"h_crr_ri_43_6_0":{"x":"-25","y":"21"},"h_crr_ri_43_7_0":{"x":"-27","y":"21"},"h_drk_ri_43_0_0":{"x":"-40","y":"62"},"h_drk_ri_43_1_0":{"x":"-43","y":"55"},"h_drk_ri_43_2_0":{"x":"-38","y":"53"},"h_drk_ri_43_3_0":{"x":"-29","y":"50"},"h_drk_ri_43_4_0":{"x":"-8","y":"52"},"h_drk_ri_43_5_0":{"x":"-6","y":"54"},"h_drk_ri_43_6_0":{"x":"-17","y":"58"},"h_drk_ri_43_7_0":{"x":"-30","y":"61"},"h_crr_ri_44_0_0":{"x":"-51","y":"40"},"h_crr_ri_44_1_0":{"x":"-44","y":"35"},"h_crr_ri_44_2_0":{"x":"-36","y":"30"},"h_crr_ri_44_3_0":{"x":"-25","y":"32"},"h_crr_ri_44_4_0":{"x":"-9","y":"36"},"h_crr_ri_44_5_0":{"x":"-13","y":"35"},"h_crr_ri_44_6_0":{"x":"-25","y":"21"},"h_crr_ri_44_7_0":{"x":"-27","y":"21"},"h_drk_ri_44_0_0":{"x":"-40","y":"62"},"h_drk_ri_44_1_0":{"x":"-43","y":"55"},"h_drk_ri_44_2_0":{"x":"-38","y":"53"},"h_drk_ri_44_3_0":{"x":"-29","y":"50"},"h_drk_ri_44_4_0":{"x":"-8","y":"52"},"h_drk_ri_44_5_0":{"x":"-6","y":"54"},"h_drk_ri_44_6_0":{"x":"-17","y":"58"},"h_drk_ri_44_7_0":{"x":"-30","y":"61"},"h_crr_ri_45_0_0":{"x":"-46","y":"49"},"h_crr_ri_45_1_0":{"x":"-39","y":"44"},"h_crr_ri_45_2_0":{"x":"-31","y":"39"},"h_crr_ri_45_3_0":{"x":"-20","y":"41"},"h_crr_ri_45_4_0":{"x":"-4","y":"45"},"h_crr_ri_45_5_0":{"x":"-8","y":"44"},"h_crr_ri_45_6_0":{"x":"-25","y":"21"},"h_crr_ri_45_7_0":{"x":"-27","y":"21"},"h_drk_ri_45_0_0":{"x":"-33","y":"62"},"h_drk_ri_45_1_0":{"x":"-34","y":"60"},"h_drk_ri_45_2_0":{"x":"-31","y":"62"},"h_drk_ri_45_3_0":{"x":"-24","y":"59"},"h_drk_ri_45_4_0":{"x":"-8","y":"56"},"h_drk_ri_45_5_0":{"x":"-6","y":"59"},"h_drk_ri_45_6_0":{"x":"-17","y":"61"},"h_drk_ri_45_7_0":{"x":"-30","y":"61"},"h_crr_ri_46_0_0":{"x":"-49","y":"47"},"h_crr_ri_46_1_0":{"x":"-42","y":"40"},"h_crr_ri_46_2_0":{"x":"-36","y":"32"},"h_crr_ri_46_3_0":{"x":"-26","y":"36"},"h_crr_ri_46_4_0":{"x":"-8","y":"40"},"h_crr_ri_46_5_0":{"x":"-12","y":"40"},"h_crr_ri_46_6_0":{"x":"-25","y":"21"},"h_crr_ri_46_7_0":{"x":"-27","y":"21"},"h_drk_ri_46_0_0":{"x":"-40","y":"69"},"h_drk_ri_46_1_0":{"x":"-43","y":"59"},"h_drk_ri_46_2_0":{"x":"-39","y":"53"},"h_drk_ri_46_3_0":{"x":"-29","y":"50"},"h_drk_ri_46_4_0":{"x":"-7","y":"54"},"h_drk_ri_46_5_0":{"x":"6","y":"61"},"h_drk_ri_46_6_0":{"x":"-14","y":"70"},"h_drk_ri_46_7_0":{"x":"-32","y":"66"},"h_crr_ri_47_0_0":{"x":"-47","y":"45"},"h_crr_ri_47_1_0":{"x":"-41","y":"40"},"h_crr_ri_47_2_0":{"x":"-30","y":"35"},"h_crr_ri_47_3_0":{"x":"-22","y":"38"},"h_crr_ri_47_4_0":{"x":"-4","y":"40"},"h_crr_ri_47_5_0":{"x":"-9","y":"41"},"h_crr_ri_47_6_0":{"x":"-25","y":"21"},"h_crr_ri_47_7_0":{"x":"-27","y":"21"},"h_drk_ri_47_0_0":{"x":"-40","y":"64"},"h_drk_ri_47_1_0":{"x":"-44","y":"58"},"h_drk_ri_47_2_0":{"x":"-38","y":"52"},"h_drk_ri_47_3_0":{"x":"-26","y":"49"},"h_drk_ri_47_4_0":{"x":"-8","y":"56"},"h_drk_ri_47_5_0":{"x":"-6","y":"59"},"h_drk_ri_47_6_0":{"x":"-16","y":"61"},"h_drk_ri_47_7_0":{"x":"-39","y":"49"},"h_crr_ri_50_0_0":{"x":"-51","y":"43"},"h_crr_ri_50_1_0":{"x":"-45","y":"38"},"h_crr_ri_50_2_0":{"x":"-34","y":"32"},"h_crr_ri_50_3_0":{"x":"-25","y":"33"},"h_crr_ri_50_4_0":{"x":"-9","y":"35"},"h_crr_ri_50_5_0":{"x":"-11","y":"37"},"h_crr_ri_50_6_0":{"x":"-39","y":"49"},"h_crr_ri_50_7_0":{"x":"-39","y":"49"},"h_drk_ri_50_0_0":{"x":"-44","y":"64"},"h_drk_ri_50_1_0":{"x":"-44","y":"60"},"h_drk_ri_50_2_0":{"x":"-41","y":"55"},"h_drk_ri_50_3_0":{"x":"-29","y":"51"},"h_drk_ri_50_4_0":{"x":"-13","y":"55"},"h_drk_ri_50_5_0":{"x":"-10","y":"60"},"h_drk_ri_50_6_0":{"x":"-20","y":"61"},"h_drk_ri_50_7_0":{"x":"-39","y":"49"},"h_crr_ri_51_0_0":{"x":"-49","y":"40"},"h_crr_ri_51_1_0":{"x":"-43","y":"36"},"h_crr_ri_51_2_0":{"x":"-35","y":"31"},"h_crr_ri_51_3_0":{"x":"-23","y":"30"},"h_crr_ri_51_4_0":{"x":"-5","y":"33"},"h_crr_ri_51_5_0":{"x":"-8","y":"34"},"h_crr_ri_51_6_0":{"x":"-39","y":"49"},"h_crr_ri_51_7_0":{"x":"-39","y":"49"},"h_drk_ri_51_0_0":{"x":"-41","y":"61"},"h_drk_ri_51_1_0":{"x":"-41","y":"57"},"h_drk_ri_51_2_0":{"x":"-39","y":"52"},"h_drk_ri_51_3_0":{"x":"-27","y":"48"},"h_drk_ri_51_4_0":{"x":"-11","y":"52"},"h_drk_ri_51_5_0":{"x":"-7","y":"57"},"h_drk_ri_51_6_0":{"x":"-17","y":"59"},"h_drk_ri_51_7_0":{"x":"-39","y":"49"},"h_crr_ri_52_0_0":{"x":"-50","y":"40"},"h_crr_ri_52_1_0":{"x":"-44","y":"36"},"h_crr_ri_52_2_0":{"x":"-35","y":"31"},"h_crr_ri_52_3_0":{"x":"-26","y":"31"},"h_crr_ri_52_4_0":{"x":"-8","y":"34"},"h_crr_ri_52_5_0":{"x":"-10","y":"34"},"h_crr_ri_52_6_0":{"x":"-39","y":"49"},"h_crr_ri_52_7_0":{"x":"-39","y":"49"},"h_drk_ri_52_0_0":{"x":"-43","y":"62"},"h_drk_ri_52_1_0":{"x":"-43","y":"57"},"h_drk_ri_52_2_0":{"x":"-41","y":"52"},"h_drk_ri_52_3_0":{"x":"-29","y":"48"},"h_drk_ri_52_4_0":{"x":"-13","y":"52"},"h_drk_ri_52_5_0":{"x":"-9","y":"57"},"h_drk_ri_52_6_0":{"x":"-19","y":"59"},"h_drk_ri_52_7_0":{"x":"-39","y":"49"},"h_crr_ri_53_0_0":{"x":"-50","y":"43"},"h_crr_ri_53_1_0":{"x":"-44","y":"38"},"h_crr_ri_53_2_0":{"x":"-35","y":"31"},"h_crr_ri_53_3_0":{"x":"-25","y":"32"},"h_crr_ri_53_4_0":{"x":"-7","y":"34"},"h_crr_ri_53_5_0":{"x":"-10","y":"37"},"h_crr_ri_53_6_0":{"x":"-39","y":"49"},"h_crr_ri_53_7_0":{"x":"-39","y":"49"},"h_drk_ri_53_0_0":{"x":"-43","y":"64"},"h_drk_ri_53_1_0":{"x":"-43","y":"60"},"h_drk_ri_53_2_0":{"x":"-40","y":"55"},"h_drk_ri_53_3_0":{"x":"-28","y":"51"},"h_drk_ri_53_4_0":{"x":"-12","y":"55"},"h_drk_ri_53_5_0":{"x":"-9","y":"60"},"h_drk_ri_53_6_0":{"x":"-19","y":"61"},"h_drk_ri_53_7_0":{"x":"-39","y":"49"},"h_crr_ri_54_0_0":{"x":"-47","y":"45"},"h_crr_ri_54_1_0":{"x":"-41","y":"40"},"h_crr_ri_54_2_0":{"x":"-30","y":"35"},"h_crr_ri_54_3_0":{"x":"-22","y":"38"},"h_crr_ri_54_4_0":{"x":"-4","y":"40"},"h_crr_ri_54_5_0":{"x":"-9","y":"41"},"h_crr_ri_54_6_0":{"x":"-25","y":"21"},"h_crr_ri_54_7_0":{"x":"-27","y":"21"},"h_drk_ri_54_0_0":{"x":"-40","y":"64"},"h_drk_ri_54_1_0":{"x":"-44","y":"58"},"h_drk_ri_54_2_0":{"x":"-38","y":"52"},"h_drk_ri_54_3_0":{"x":"-26","y":"49"},"h_drk_ri_54_4_0":{"x":"-8","y":"56"},"h_drk_ri_54_5_0":{"x":"-6","y":"59"},"h_drk_ri_54_6_0":{"x":"-16","y":"61"},"h_drk_ri_54_7_0":{"x":"-39","y":"49"},"h_crr_ri_48_0_0":{"x":"-51","y":"38"},"h_crr_ri_48_1_0":{"x":"-44","y":"33"},"h_crr_ri_48_2_0":{"x":"-36","y":"28"},"h_crr_ri_48_3_0":{"x":"-25","y":"30"},"h_crr_ri_48_4_0":{"x":"-9","y":"34"},"h_crr_ri_48_5_0":{"x":"-13","y":"33"},"h_crr_ri_48_6_0":{"x":"-25","y":"21"},"h_crr_ri_48_7_0":{"x":"-27","y":"21"},"h_drk_ri_48_0_0":{"x":"-39","y":"61"},"h_drk_ri_48_1_0":{"x":"-43","y":"55"},"h_drk_ri_48_2_0":{"x":"-38","y":"53"},"h_drk_ri_48_3_0":{"x":"-29","y":"47"},"h_drk_ri_48_5_0":{"x":"-7","y":"55"},"h_drk_ri_48_6_0":{"x":"-22","y":"63"},"h_drk_ri_48_7_0":{"x":"-33","y":"58"},"h_drk_ri_48_4_0":{"x":"-11","y":"53"},"h_crr_ri_55_0_0":{"x":"-51","y":"38"},"h_crr_ri_55_1_0":{"x":"-44","y":"33"},"h_crr_ri_55_2_0":{"x":"-36","y":"28"},"h_crr_ri_55_3_0":{"x":"-25","y":"30"},"h_crr_ri_55_4_0":{"x":"-9","y":"34"},"h_crr_ri_55_5_0":{"x":"-13","y":"33"},"h_crr_ri_55_6_0":{"x":"-25","y":"21"},"h_crr_ri_55_7_0":{"x":"-27","y":"21"},"h_drk_ri_55_0_0":{"x":"-39","y":"61"},"h_drk_ri_55_1_0":{"x":"-43","y":"55"},"h_drk_ri_55_2_0":{"x":"-38","y":"53"},"h_drk_ri_55_3_0":{"x":"-29","y":"47"},"h_drk_ri_55_5_0":{"x":"-7","y":"55"},"h_drk_ri_55_6_0":{"x":"-22","y":"63"},"h_drk_ri_55_7_0":{"x":"-33","y":"58"},"h_drk_ri_55_4_0":{"x":"-11","y":"53"},"h_crr_ri_56_0_0":{"x":"-52","y":"41"},"h_crr_ri_56_1_0":{"x":"-45","y":"34"},"h_crr_ri_56_2_0":{"x":"-34","y":"31"},"h_crr_ri_56_3_0":{"x":"-24","y":"33"},"h_crr_ri_56_4_0":{"x":"-7","y":"36"},"h_crr_ri_56_5_0":{"x":"-14","y":"33"},"h_crr_ri_56_6_0":{"x":"-25","y":"21"},"h_crr_ri_56_7_0":{"x":"-27","y":"21"},"h_drk_ri_56_0_0":{"x":"-36","y":"60"},"h_drk_ri_56_1_0":{"x":"-40","y":"55"},"h_drk_ri_56_2_0":{"x":"-38","y":"53"},"h_drk_ri_56_3_0":{"x":"-30","y":"49"},"h_drk_ri_56_5_0":{"x":"-4","y":"53"},"h_drk_ri_56_6_0":{"x":"-20","y":"66"},"h_drk_ri_56_7_0":{"x":"-36","y":"58"},"h_drk_ri_56_4_0":{"x":"-9","y":"53"},"h_crr_ri_57_0_0":{"x":"-50","y":"40"},"h_crr_ri_57_1_0":{"x":"-44","y":"36"},"h_crr_ri_57_2_0":{"x":"-35","y":"31"},"h_crr_ri_57_3_0":{"x":"-26","y":"31"},"h_crr_ri_57_4_0":{"x":"-8","y":"34"},"h_crr_ri_57_5_0":{"x":"-10","y":"34"},"h_crr_ri_57_6_0":{"x":"-39","y":"49"},"h_crr_ri_57_7_0":{"x":"-39","y":"49"},"h_drk_ri_57_0_0":{"x":"-43","y":"62"},"h_drk_ri_57_1_0":{"x":"-43","y":"57"},"h_drk_ri_57_2_0":{"x":"-41","y":"52"},"h_drk_ri_57_3_0":{"x":"-29","y":"48"},"h_drk_ri_57_4_0":{"x":"-13","y":"52"},"h_drk_ri_57_5_0":{"x":"-9","y":"57"},"h_drk_ri_57_6_0":{"x":"-19","y":"59"},"h_drk_ri_57_7_0":{"x":"-39","y":"49"},"h_crr_ri_58_0_0":{"x":"-50","y":"40"},"h_crr_ri_58_1_0":{"x":"-44","y":"36"},"h_crr_ri_58_2_0":{"x":"-35","y":"31"},"h_crr_ri_58_3_0":{"x":"-26","y":"31"},"h_crr_ri_58_4_0":{"x":"-8","y":"34"},"h_crr_ri_58_5_0":{"x":"-10","y":"34"},"h_crr_ri_58_6_0":{"x":"-39","y":"49"},"h_crr_ri_58_7_0":{"x":"-39","y":"49"},"h_drk_ri_58_0_0":{"x":"-43","y":"62"},"h_drk_ri_58_1_0":{"x":"-43","y":"57"},"h_drk_ri_58_2_0":{"x":"-41","y":"52"},"h_drk_ri_58_3_0":{"x":"-29","y":"48"},"h_drk_ri_58_4_0":{"x":"-13","y":"52"},"h_drk_ri_58_5_0":{"x":"-9","y":"57"},"h_drk_ri_58_6_0":{"x":"-19","y":"59"},"h_drk_ri_58_7_0":{"x":"-39","y":"49"},"h_crr_ri_59_0_0":{"x":"-50","y":"40"},"h_crr_ri_59_1_0":{"x":"-44","y":"36"},"h_crr_ri_59_2_0":{"x":"-35","y":"31"},"h_crr_ri_59_3_0":{"x":"-26","y":"31"},"h_crr_ri_59_4_0":{"x":"-8","y":"34"},"h_crr_ri_59_5_0":{"x":"-10","y":"34"},"h_crr_ri_59_6_0":{"x":"-39","y":"49"},"h_crr_ri_59_7_0":{"x":"-39","y":"49"},"h_drk_ri_59_0_0":{"x":"-43","y":"62"},"h_drk_ri_59_1_0":{"x":"-43","y":"57"},"h_drk_ri_59_2_0":{"x":"-41","y":"52"},"h_drk_ri_59_3_0":{"x":"-29","y":"48"},"h_drk_ri_59_4_0":{"x":"-13","y":"52"},"h_drk_ri_59_5_0":{"x":"-9","y":"57"},"h_drk_ri_59_6_0":{"x":"-19","y":"59"},"h_drk_ri_59_7_0":{"x":"-39","y":"49"},"h_crr_ri_60_0_0":{"x":"-50","y":"46"},"h_crr_ri_60_1_0":{"x":"-43","y":"39"},"h_crr_ri_60_2_0":{"x":"-32","y":"36"},"h_crr_ri_60_3_0":{"x":"-22","y":"38"},"h_crr_ri_60_4_0":{"x":"-5","y":"41"},"h_crr_ri_60_5_0":{"x":"-12","y":"38"},"h_crr_ri_60_6_0":{"x":"-25","y":"21"},"h_crr_ri_60_7_0":{"x":"-27","y":"21"},"h_drk_ri_60_0_0":{"x":"-34","y":"58"},"h_drk_ri_60_1_0":{"x":"-38","y":"57"},"h_drk_ri_60_2_0":{"x":"-36","y":"53"},"h_drk_ri_60_3_0":{"x":"-28","y":"54"},"h_drk_ri_60_5_0":{"x":"-8","y":"55"},"h_drk_ri_60_6_0":{"x":"-19","y":"64"},"h_drk_ri_60_7_0":{"x":"-36","y":"58"},"h_drk_ri_60_4_0":{"x":"-8","y":"52"},"h_crr_ri_61_0_0":{"x":"-49","y":"42"},"h_crr_ri_61_1_0":{"x":"-41","y":"37"},"h_crr_ri_61_2_0":{"x":"-35","y":"32"},"h_crr_ri_61_3_0":{"x":"-24","y":"34"},"h_crr_ri_61_4_0":{"x":"-8","y":"38"},"h_crr_ri_61_5_0":{"x":"-10","y":"37"},"h_crr_ri_61_6_0":{"x":"-25","y":"21"},"h_crr_ri_61_7_0":{"x":"-27","y":"21"},"h_drk_ri_61_0_0":{"x":"-38","y":"62"},"h_drk_ri_61_1_0":{"x":"-42","y":"58"},"h_drk_ri_61_2_0":{"x":"-35","y":"54"},"h_drk_ri_61_3_0":{"x":"-28","y":"52"},"h_drk_ri_61_4_0":{"x":"-7","y":"53"},"h_drk_ri_61_5_0":{"x":"-5","y":"58"},"h_crr_ri_62_0_0":{"x":"-49","y":"44"},"h_crr_ri_62_1_0":{"x":"-42","y":"37"},"h_crr_ri_62_2_0":{"x":"-31","y":"34"},"h_crr_ri_62_3_0":{"x":"-21","y":"36"},"h_crr_ri_62_4_0":{"x":"-5","y":"38"},"h_crr_ri_62_5_0":{"x":"-11","y":"36"},"h_crr_ri_62_6_0":{"x":"-25","y":"21"},"h_crr_ri_62_7_0":{"x":"-27","y":"21"},"h_drk_ri_62_0_0":{"x":"-31","y":"59"},"h_drk_ri_62_1_0":{"x":"-40","y":"56"},"h_drk_ri_62_2_0":{"x":"-40","y":"53"},"h_drk_ri_62_3_0":{"x":"-27","y":"50"},"h_drk_ri_62_4_0":{"x":"0","y":"55"},"h_drk_ri_62_5_0":{"x":"-1","y":"63"},"h_drk_ri_62_6_0":{"x":"-6","y":"62"},"h_drk_ri_62_7_0":{"x":"-18","y":"53"},"h_crr_ri_63_0_0":{"x":"-49","y":"46"},"h_crr_ri_63_1_0":{"x":"-41","y":"41"},"h_crr_ri_63_2_0":{"x":"-36","y":"35"},"h_crr_ri_63_3_0":{"x":"-25","y":"37"},"h_crr_ri_63_4_0":{"x":"-9","y":"41"},"h_crr_ri_63_5_0":{"x":"-8","y":"41"},"h_crr_ri_63_6_0":{"x":"-25","y":"21"},"h_crr_ri_63_7_0":{"x":"-27","y":"21"},"h_drk_ri_63_0_0":{"x":"-37","y":"67"},"h_drk_ri_63_1_0":{"x":"-40","y":"59"},"h_drk_ri_63_2_0":{"x":"-32","y":"56"},"h_drk_ri_63_3_0":{"x":"-29","y":"56"},"h_drk_ri_63_4_0":{"x":"-6","y":"54"},"h_drk_ri_63_5_0":{"x":"-4","y":"59"},"h_drk_ri_63_6_0":{"x":"-14","y":"60"},"h_drk_ri_63_7_0":{"x":"-24","y":"66"},"h_crr_ri_64_0_0":{"x":"-49","y":"46"},"h_crr_ri_64_1_0":{"x":"-41","y":"41"},"h_crr_ri_64_2_0":{"x":"-36","y":"35"},"h_crr_ri_64_3_0":{"x":"-25","y":"37"},"h_crr_ri_64_4_0":{"x":"-9","y":"41"},"h_crr_ri_64_5_0":{"x":"-8","y":"41"},"h_crr_ri_64_6_0":{"x":"-25","y":"21"},"h_crr_ri_64_7_0":{"x":"-27","y":"21"},"h_drk_ri_64_0_0":{"x":"-35","y":"67"},"h_drk_ri_64_1_0":{"x":"-39","y":"60"},"h_drk_ri_64_2_0":{"x":"-32","y":"56"},"h_drk_ri_64_3_0":{"x":"-28","y":"56"},"h_drk_ri_64_4_0":{"x":"-5","y":"53"},"h_drk_ri_64_5_0":{"x":"-3","y":"60"},"h_drk_ri_64_6_0":{"x":"-12","y":"61"},"h_drk_ri_64_7_0":{"x":"-25","y":"65"},"h_crr_ri_65_0_0":{"x":"-50","y":"39"},"h_crr_ri_65_1_0":{"x":"-45","y":"34"},"h_crr_ri_65_2_0":{"x":"-33","y":"29"},"h_crr_ri_65_3_0":{"x":"-24","y":"30"},"h_crr_ri_65_4_0":{"x":"-7","y":"34"},"h_crr_ri_65_5_0":{"x":"-12","y":"37"},"h_crr_ri_65_6_0":{"x":"-39","y":"49"},"h_crr_ri_65_7_0":{"x":"-39","y":"49"},"h_drk_ri_65_0_0":{"x":"-41","y":"61"},"h_drk_ri_65_1_0":{"x":"-45","y":"60"},"h_drk_ri_65_2_0":{"x":"-40","y":"51"},"h_drk_ri_65_3_0":{"x":"-28","y":"46"},"h_drk_ri_65_4_0":{"x":"-9","y":"57"},"h_drk_ri_65_5_0":{"x":"-8","y":"60"},"h_drk_ri_65_6_0":{"x":"-18","y":"62"},"h_drk_ri_65_7_0":{"x":"-39","y":"49"},"h_crr_ri_66_0_0":{"x":"-49","y":"45"},"h_crr_ri_66_1_0":{"x":"-45","y":"40"},"h_crr_ri_66_2_0":{"x":"-35","y":"33"},"h_crr_ri_66_3_0":{"x":"-25","y":"34"},"h_crr_ri_66_4_0":{"x":"-4","y":"35"},"h_crr_ri_66_5_0":{"x":"-8","y":"37"},"h_crr_ri_66_6_0":{"x":"-25","y":"21"},"h_crr_ri_66_7_0":{"x":"-27","y":"21"},"h_drk_ri_66_0_0":{"x":"-38","y":"59"},"h_drk_ri_66_1_0":{"x":"-41","y":"56"},"h_drk_ri_66_2_0":{"x":"-39","y":"53"},"h_drk_ri_66_3_0":{"x":"-27","y":"50"},"h_drk_ri_66_4_0":{"x":"-11","y":"55"},"h_drk_ri_66_5_0":{"x":"-6","y":"56"},"h_drk_ri_66_6_0":{"x":"-16","y":"59"},"h_drk_ri_66_7_0":{"x":"-32","y":"58"},"h_drk_ri_67_6_0":{"x":"-2","y":"59"},"h_drk_ri_67_5_0":{"x":"-1","y":"55"},"h_drk_ri_67_4_0":{"x":"-1","y":"53"},"h_drk_ri_67_3_0":{"x":"-27","y":"50"},"h_drk_ri_67_2_0":{"x":"-39","y":"52"},"h_drk_ri_67_1_0":{"x":"-41","y":"56"},"h_drk_ri_67_0_0":{"x":"-29","y":"62"},"h_drk_ri_67_7_0":{"x":"-39","y":"49"},"h_crr_ri_67_0_0":{"x":"-51","y":"50"},"h_crr_ri_67_1_0":{"x":"-44","y":"45"},"h_crr_ri_67_2_0":{"x":"-34","y":"34"},"h_crr_ri_67_3_0":{"x":"-24","y":"37"},"h_crr_ri_67_4_0":{"x":"-8","y":"40"},"h_crr_ri_67_5_0":{"x":"-10","y":"45"},"h_crr_ri_67_6_0":{"x":"-25","y":"21"},"h_crr_ri_67_7_0":{"x":"-27","y":"21"},"h_crr_ri_68_0_0":{"x":"-49","y":"45"},"h_crr_ri_68_1_0":{"x":"-45","y":"40"},"h_crr_ri_68_2_0":{"x":"-35","y":"34"},"h_crr_ri_68_3_0":{"x":"-25","y":"34"},"h_crr_ri_68_4_0":{"x":"-3","y":"35"},"h_crr_ri_68_5_0":{"x":"-6","y":"37"},"h_crr_ri_68_7_0":{"x":"-27","y":"21"},"h_crr_ri_68_6_0":{"x":"-25","y":"21"},"h_drk_ri_68_0_0":{"x":"-42","y":"65"},"h_drk_ri_68_1_0":{"x":"-45","y":"60"},"h_drk_ri_68_2_0":{"x":"-40","y":"55"},"h_drk_ri_68_3_0":{"x":"-25","y":"46"},"h_drk_ri_68_4_0":{"x":"-1","y":"60"},"h_drk_ri_68_5_0":{"x":"1","y":"63"},"h_drk_ri_68_6_0":{"x":"-10","y":"63"},"h_drk_ri_68_7_0":{"x":"-39","y":"49"},"h_crr_ri_69_0_0":{"x":"-48","y":"41"},"h_crr_ri_69_1_0":{"x":"-41","y":"36"},"h_crr_ri_69_2_0":{"x":"-31","y":"31"},"h_crr_ri_69_3_0":{"x":"-21","y":"33"},"h_crr_ri_69_4_0":{"x":"-7","y":"35"},"h_crr_ri_69_5_0":{"x":"-14","y":"36"},"h_crr_ri_69_6_0":{"x":"-25","y":"21"},"h_crr_ri_69_7_0":{"x":"-27","y":"21"},"h_drk_ri_69_0_0":{"x":"-43","y":"61"},"h_drk_ri_69_1_0":{"x":"-47","y":"53"},"h_drk_ri_69_2_0":{"x":"-42","y":"49"},"h_drk_ri_69_3_0":{"x":"-27","y":"47"},"h_drk_ri_69_4_0":{"x":"-11","y":"56"},"h_drk_ri_69_5_0":{"x":"-2","y":"53"},"h_drk_ri_69_6_0":{"x":"-12","y":"58"},"h_drk_ri_69_7_0":{"x":"-39","y":"49"},"h_crr_ri_70_0_0":{"x":"-49","y":"43"},"h_crr_ri_70_1_0":{"x":"-44","y":"39"},"h_crr_ri_70_2_0":{"x":"-33","y":"33"},"h_crr_ri_70_3_0":{"x":"-24","y":"38"},"h_crr_ri_70_4_0":{"x":"-8","y":"41"},"h_crr_ri_70_5_0":{"x":"-10","y":"41"},"h_crr_ri_70_6_0":{"x":"-39","y":"49"},"h_crr_ri_70_7_0":{"x":"-39","y":"49"},"h_drk_ri_70_0_0":{"x":"-39","y":"63"},"h_drk_ri_70_1_0":{"x":"-44","y":"58"},"h_drk_ri_70_2_0":{"x":"-39","y":"51"},"h_drk_ri_70_3_0":{"x":"-27","y":"47"},"h_drk_ri_70_4_0":{"x":"-4","y":"55"},"h_drk_ri_70_5_0":{"x":"-3","y":"58"},"h_drk_ri_70_6_0":{"x":"-10","y":"60"},"h_drk_ri_70_7_0":{"x":"-39","y":"49"},"h_crr_ri_71_0_0":{"x":"-51","y":"38"},"h_crr_ri_71_1_0":{"x":"-44","y":"35"},"h_crr_ri_71_2_0":{"x":"-36","y":"31"},"h_crr_ri_71_3_0":{"x":"-25","y":"34"},"h_crr_ri_71_4_0":{"x":"-9","y":"40"},"h_crr_ri_71_5_0":{"x":"-13","y":"35"},"h_crr_ri_71_6_0":{"x":"-25","y":"21"},"h_crr_ri_71_7_0":{"x":"-27","y":"21"},"h_drk_ri_71_0_0":{"x":"-39","y":"61"},"h_drk_ri_71_1_0":{"x":"-43","y":"55"},"h_drk_ri_71_2_0":{"x":"-38","y":"53"},"h_drk_ri_71_3_0":{"x":"-29","y":"47"},"h_drk_ri_71_5_0":{"x":"-7","y":"55"},"h_drk_ri_71_6_0":{"x":"-22","y":"63"},"h_drk_ri_71_7_0":{"x":"-33","y":"58"},"h_drk_ri_71_4_0":{"x":"-11","y":"53"},"h_crr_ri_72_0_0":{"x":"-49","y":"45"},"h_crr_ri_72_1_0":{"x":"-45","y":"40"},"h_crr_ri_72_2_0":{"x":"-35","y":"34"},"h_crr_ri_72_3_0":{"x":"-25","y":"34"},"h_crr_ri_72_4_0":{"x":"-3","y":"35"},"h_crr_ri_72_5_0":{"x":"-6","y":"37"},"h_crr_ri_72_7_0":{"x":"-27","y":"21"},"h_crr_ri_72_6_0":{"x":"-25","y":"21"},"h_drk_ri_72_0_0":{"x":"-42","y":"65"},"h_drk_ri_72_1_0":{"x":"-45","y":"60"},"h_drk_ri_72_2_0":{"x":"-40","y":"55"},"h_drk_ri_72_3_0":{"x":"-25","y":"46"},"h_drk_ri_72_4_0":{"x":"-1","y":"60"},"h_drk_ri_72_5_0":{"x":"1","y":"63"},"h_drk_ri_72_6_0":{"x":"-10","y":"63"},"h_drk_ri_72_7_0":{"x":"-39","y":"49"},"h_crr_ri_73_0_0":{"x":"-47","y":"47"},"h_crr_ri_73_1_0":{"x":"-41","y":"43"},"h_crr_ri_73_2_0":{"x":"-31","y":"38"},"h_crr_ri_73_3_0":{"x":"-25","y":"38"},"h_crr_ri_73_4_0":{"x":"-8","y":"42"},"h_crr_ri_73_5_0":{"x":"-10","y":"42"},"h_crr_ri_73_6_0":{"x":"-25","y":"21"},"h_crr_ri_73_7_0":{"x":"-27","y":"21"},"h_drk_ri_73_0_0":{"x":"-38","y":"62"},"h_drk_ri_73_1_0":{"x":"-39","y":"58"},"h_drk_ri_73_2_0":{"x":"-36","y":"57"},"h_drk_ri_73_3_0":{"x":"-27","y":"53"},"h_drk_ri_73_4_0":{"x":"-8","y":"57"},"h_drk_ri_73_5_0":{"x":"-2","y":"59"},"h_drk_ri_73_6_0":{"x":"-7","y":"62"},"h_drk_ri_73_7_0":{"x":"-18","y":"53"},"h_crr_ri_74_0_0":{"x":"-51","y":"43"},"h_crr_ri_74_1_0":{"x":"-44","y":"38"},"h_crr_ri_74_2_0":{"x":"-36","y":"31"},"h_crr_ri_74_3_0":{"x":"-25","y":"33"},"h_crr_ri_74_4_0":{"x":"-9","y":"36"},"h_crr_ri_74_5_0":{"x":"-12","y":"37"},"h_crr_ri_74_6_0":{"x":"-25","y":"21"},"h_crr_ri_74_7_0":{"x":"-27","y":"21"},"h_drk_ri_74_0_0":{"x":"-37","y":"59"},"h_drk_ri_74_1_0":{"x":"-41","y":"56"},"h_drk_ri_74_2_0":{"x":"-35","y":"52"},"h_drk_ri_74_3_0":{"x":"-29","y":"52"},"h_drk_ri_74_4_0":{"x":"-6","y":"53"},"h_drk_ri_74_5_0":{"x":"-2","y":"56"},"h_drk_ri_74_6_0":{"x":"-13","y":"59"},"h_drk_ri_74_7_0":{"x":"-36","y":"50"},"h_crr_ri_75_0_0":{"x":"-51","y":"38"},"h_crr_ri_75_1_0":{"x":"-44","y":"33"},"h_crr_ri_75_2_0":{"x":"-36","y":"28"},"h_crr_ri_75_3_0":{"x":"-25","y":"30"},"h_crr_ri_75_4_0":{"x":"-9","y":"34"},"h_crr_ri_75_5_0":{"x":"-13","y":"33"},"h_crr_ri_75_6_0":{"x":"-25","y":"21"},"h_crr_ri_75_7_0":{"x":"-27","y":"21"},"h_drk_ri_75_0_0":{"x":"-39","y":"61"},"h_drk_ri_75_1_0":{"x":"-43","y":"55"},"h_drk_ri_75_2_0":{"x":"-38","y":"53"},"h_drk_ri_75_3_0":{"x":"-29","y":"47"},"h_drk_ri_75_5_0":{"x":"-7","y":"55"},"h_drk_ri_75_6_0":{"x":"-22","y":"63"},"h_drk_ri_75_7_0":{"x":"-33","y":"58"},"h_drk_ri_75_4_0":{"x":"-11","y":"53"},"h_crr_ri_76_1_0":{"x":"-39","y":"51"},"h_crr_ri_76_2_0":{"x":"-28","y":"45"},"h_crr_ri_76_0_0":{"x":"-46","y":"54"},"h_crr_ri_76_3_0":{"x":"-18","y":"48"},"h_crr_ri_76_4_0":{"x":"-4","y":"51"},"h_crr_ri_76_5_0":{"x":"-13","y":"52"},"h_crr_ri_76_6_0":{"x":"-20","y":"53"},"h_crr_ri_76_7_0":{"x":"-34","y":"52"},"h_crr_ri_77_1_0":{"x":"-39","y":"51"},"h_crr_ri_77_2_0":{"x":"-28","y":"45"},"h_crr_ri_77_0_0":{"x":"-46","y":"54"},"h_crr_ri_77_3_0":{"x":"-18","y":"48"},"h_crr_ri_77_4_0":{"x":"-4","y":"51"},"h_crr_ri_77_5_0":{"x":"-13","y":"52"},"h_crr_ri_77_6_0":{"x":"-20","y":"53"},"h_crr_ri_77_7_0":{"x":"-34","y":"52"},"h_crr_ri_78_7_0":{"x":"-29","y":"57"},"h_crr_ri_78_6_0":{"x":"-23","y":"61"},"h_crr_ri_78_5_0":{"x":"-6","y":"61"},"h_crr_ri_78_4_0":{"x":"1","y":"59"},"h_crr_ri_78_3_0":{"x":"-18","y":"47"},"h_crr_ri_78_2_0":{"x":"-27","y":"56"},"h_crr_ri_78_1_0":{"x":"-40","y":"61"},"h_crr_ri_78_0_0":{"x":"-42","y":"62"},"h_crr_ri_79_0_0":{"x":"-49","y":"44"},"h_crr_ri_79_1_0":{"x":"-45","y":"38"},"h_crr_ri_79_2_0":{"x":"-35","y":"33"},"h_crr_ri_79_3_0":{"x":"-25","y":"35"},"h_crr_ri_79_4_0":{"x":"1","y":"37"},"h_crr_ri_79_5_0":{"x":"-7","y":"39"},"h_crr_ri_80_0_0":{"x":"-49","y":"44"},"h_crr_ri_80_1_0":{"x":"-45","y":"38"},"h_crr_ri_80_2_0":{"x":"-35","y":"33"},"h_crr_ri_80_3_0":{"x":"-25","y":"35"},"h_crr_ri_80_4_0":{"x":"1","y":"37"},"h_crr_ri_80_5_0":{"x":"-7","y":"39"},"h_crr_ri_81_0_0":{"x":"-49","y":"44"},"h_crr_ri_81_1_0":{"x":"-45","y":"38"},"h_crr_ri_81_2_0":{"x":"-35","y":"33"},"h_crr_ri_81_3_0":{"x":"-25","y":"35"},"h_crr_ri_81_4_0":{"x":"1","y":"37"},"h_crr_ri_81_5_0":{"x":"-7","y":"39"},"h_crr_ri_82_0_0":{"x":"-49","y":"53"},"h_crr_ri_82_1_0":{"x":"-42","y":"50"},"h_crr_ri_82_2_0":{"x":"-31","y":"45"},"h_crr_ri_82_3_0":{"x":"-20","y":"50"},"h_crr_ri_82_4_0":{"x":"-1","y":"51"},"h_crr_ri_82_5_0":{"x":"-7","y":"51"},"h_crr_ri_82_6_0":{"x":"92","y":"52"},"h_crr_ri_83_5_0":{"x":"-12","y":"42"},"h_crr_ri_83_4_0":{"x":"-3","y":"41"},"h_crr_ri_83_3_0":{"x":"-19","y":"36"},"h_crr_ri_83_2_0":{"x":"-30","y":"34"},"h_crr_ri_83_1_0":{"x":"-41","y":"40"},"h_crr_ri_83_0_0":{"x":"-48","y":"45"},"h_crr_ri_84_5_0":{"x":"-12","y":"42"},"h_crr_ri_84_4_0":{"x":"-3","y":"41"},"h_crr_ri_84_3_0":{"x":"-19","y":"36"},"h_crr_ri_84_2_0":{"x":"-30","y":"34"},"h_crr_ri_84_1_0":{"x":"-41","y":"40"},"h_crr_ri_84_0_0":{"x":"-48","y":"45"},"h_crr_ri_85_5_0":{"x":"-12","y":"42"},"h_crr_ri_85_4_0":{"x":"-3","y":"41"},"h_crr_ri_85_3_0":{"x":"-19","y":"36"},"h_crr_ri_85_2_0":{"x":"-30","y":"34"},"h_crr_ri_85_1_0":{"x":"-41","y":"40"},"h_crr_ri_85_0_0":{"x":"-48","y":"45"},"h_crr_ri_87_0_0":{"x":"-44","y":"49"},"h_crr_ri_87_4_0":{"x":"-11","y":"41"},"h_crr_ri_87_2_0":{"x":"-35","y":"37"},"h_crr_ri_87_3_0":{"x":"-26","y":"38"},"h_crr_ri_87_1_0":{"x":"-44","y":"44"},"h_crr_ri_87_5_0":{"x":"-16","y":"43"},"h_crr_ri_89_0_0":{"x":"-52","y":"40"},"h_crr_ri_89_1_0":{"x":"-45","y":"35"},"h_crr_ri_89_2_0":{"x":"-34","y":"29"},"h_crr_ri_89_3_0":{"x":"-25","y":"31"},"h_crr_ri_89_4_0":{"x":"-10","y":"35"},"h_crr_ri_89_5_0":{"x":"-16","y":"36"},"h_crr_ri_90_7_0":{"x":"-38","y":"49"},"h_crr_ri_90_6_0":{"x":"-20","y":"41"},"h_crr_ri_90_5_0":{"x":"-10","y":"42"},"h_crr_ri_90_4_0":{"x":"-2","y":"41"},"h_crr_ri_90_3_0":{"x":"-21","y":"42"},"h_crr_ri_90_2_0":{"x":"-29","y":"36"},"h_crr_ri_90_1_0":{"x":"-40","y":"42"},"h_crr_ri_90_0_0":{"x":"-46","y":"46"},"h_crr_ri_91_4_0":{"x":"-3","y":"34"},"h_crr_ri_91_2_0":{"x":"-27","y":"30"},"h_crr_ri_91_1_0":{"x":"-43","y":"34"},"h_crr_ri_91_5_0":{"x":"-17","y":"36"},"h_crr_ri_91_6_0":{"x":"-22","y":"40"},"h_crr_ri_91_0_0":{"x":"-44","y":"40"},"h_crr_ri_91_3_0":{"x":"-18","y":"31"},"h_crr_ri_91_7_0":{"x":"-31","y":"34"},"h_crr_ri_92_0_0":{"x":"-52","y":"39"},"h_crr_ri_92_1_0":{"x":"-46","y":"33"},"h_crr_ri_92_2_0":{"x":"-34","y":"28"},"h_crr_ri_92_3_0":{"x":"-25","y":"29"},"h_crr_ri_92_4_0":{"x":"-10","y":"34"},"h_crr_ri_92_5_0":{"x":"-18","y":"34"},"h_drk_ri_92_0_0":{"x":"-41","y":"57"},"h_drk_ri_92_1_0":{"x":"-42","y":"54"},"h_drk_ri_92_2_0":{"x":"-38","y":"51"},"h_drk_ri_92_4_0":{"x":"-17","y":"54"},"h_drk_ri_92_5_0":{"x":"-14","y":"55"},"h_drk_ri_92_3_0":{"x":"-29","y":"48"},"h_crr_ri_93_0_0":{"x":"-52","y":"39"},"h_crr_ri_93_1_0":{"x":"-46","y":"33"},"h_crr_ri_93_2_0":{"x":"-34","y":"28"},"h_crr_ri_93_4_0":{"x":"-10","y":"34"},"h_crr_ri_93_5_0":{"x":"-18","y":"34"},"h_crr_ri_93_3_0":{"x":"-25","y":"29"},"h_drk_ri_93_0_0":{"x":"-41","y":"57"},"h_drk_ri_93_1_0":{"x":"-42","y":"54"},"h_drk_ri_93_2_0":{"x":"-38","y":"51"},"h_drk_ri_93_4_0":{"x":"-17","y":"54"},"h_drk_ri_93_5_0":{"x":"-14","y":"55"},"h_drk_ri_93_3_0":{"x":"-29","y":"48"},"h_crr_ri_94_0_0":{"x":"-52","y":"39"},"h_crr_ri_94_1_0":{"x":"-46","y":"33"},"h_crr_ri_94_2_0":{"x":"-34","y":"28"},"h_crr_ri_94_4_0":{"x":"-10","y":"34"},"h_crr_ri_94_5_0":{"x":"-18","y":"34"},"h_crr_ri_94_3_0":{"x":"-25","y":"29"},"h_drk_ri_94_0_0":{"x":"-41","y":"57"},"h_drk_ri_94_1_0":{"x":"-42","y":"54"},"h_drk_ri_94_2_0":{"x":"-38","y":"51"},"h_drk_ri_94_4_0":{"x":"-17","y":"54"},"h_drk_ri_94_5_0":{"x":"-14","y":"55"},"h_drk_ri_94_3_0":{"x":"-29","y":"48"},"h_crr_ri_95_5_0":{"x":"-12","y":"48"},"h_crr_ri_95_4_0":{"x":"-2","y":"47"},"h_crr_ri_95_3_0":{"x":"-19","y":"43"},"h_crr_ri_95_2_0":{"x":"-31","y":"39"},"h_crr_ri_95_1_0":{"x":"-43","y":"48"},"h_crr_ri_95_0_0":{"x":"-48","y":"53"},"h_crr_ri_97_5_0":{"x":"-13","y":"58"},"h_crr_ri_97_4_0":{"x":"-5","y":"57"},"h_crr_ri_97_3_0":{"x":"-22","y":"53"},"h_crr_ri_97_2_0":{"x":"-29","y":"51"},"h_crr_ri_97_1_0":{"x":"-42","y":"58"},"h_crr_ri_97_0_0":{"x":"-47","y":"60"},"h_crr_ri_98_5_0":{"x":"-13","y":"58"},"h_crr_ri_98_4_0":{"x":"-5","y":"57"},"h_crr_ri_98_3_0":{"x":"-22","y":"53"},"h_crr_ri_98_2_0":{"x":"-29","y":"51"},"h_crr_ri_98_1_0":{"x":"-42","y":"58"},"h_crr_ri_98_0_0":{"x":"-47","y":"60"},"h_crr_ri_99_0_0":{"x":"-39","y":"54"},"h_crr_ri_99_1_0":{"x":"-34","y":"49"},"h_crr_ri_99_2_0":{"x":"-23","y":"43"},"h_crr_ri_99_3_0":{"x":"-19","y":"45"},"h_crr_ri_99_4_0":{"x":"1","y":"49"},"h_crr_ri_99_5_0":{"x":"-7","y":"51"},"h_crr_ri_99_6_0":{"x":"-16","y":"50"},"h_crr_ri_99_7_0":{"x":"-30","y":"49"},"h_crr_ri_100_0_0":{"x":"-47","y":"45"},"h_crr_ri_100_1_0":{"x":"-42","y":"40"},"h_crr_ri_100_2_0":{"x":"-32","y":"34"},"h_crr_ri_100_3_0":{"x":"-23","y":"35"},"h_crr_ri_100_4_0":{"x":"-2","y":"39"},"h_crr_ri_100_5_0":{"x":"-10","y":"40"},"h_crr_ri_101_0_0":{"x":"-53","y":"44"},"h_crr_ri_101_1_0":{"x":"-46","y":"39"},"h_crr_ri_101_2_0":{"x":"-35","y":"32"},"h_crr_ri_101_4_0":{"x":"-7","y":"39"},"h_crr_ri_101_5_0":{"x":"-16","y":"40"},"h_crr_ri_101_3_0":{"x":"-25","y":"36"},"h_crr_ri_102_5_0":{"x":"-8","y":"42"},"h_crr_ri_102_4_0":{"x":"1","y":"40"},"h_crr_ri_102_3_0":{"x":"-24","y":"37"},"h_crr_ri_102_2_0":{"x":"-34","y":"34"},"h_crr_ri_102_1_0":{"x":"-47","y":"41"},"h_crr_ri_102_0_0":{"x":"-47","y":"48"},"h_crr_ri_103_0_0":{"x":"-52","y":"49"},"h_crr_ri_103_1_0":{"x":"-44","y":"44"},"h_crr_ri_103_2_0":{"x":"-33","y":"38"},"h_crr_ri_103_4_0":{"x":"-10","y":"45"},"h_crr_ri_103_3_0":{"x":"-25","y":"41"},"h_crr_ri_103_5_0":{"x":"-18","y":"45"},"h_crr_ri_105_5_0":{"x":"-14","y":"45"},"h_crr_ri_105_4_0":{"x":"-5","y":"44"},"h_crr_ri_105_3_0":{"x":"-23","y":"41"},"h_crr_ri_105_2_0":{"x":"-32","y":"38"},"h_crr_ri_105_1_0":{"x":"-43","y":"45"},"h_crr_ri_105_0_0":{"x":"-50","y":"48"},"h_drk_ri_105_5_0":{"x":"-7","y":"55"},"h_drk_ri_105_6_0":{"x":"-13","y":"59"},"h_drk_ri_105_4_0":{"x":"-10","y":"55"},"h_drk_ri_105_3_0":{"x":"-24","y":"57"},"h_drk_ri_105_2_0":{"x":"-32","y":"51"},"h_drk_ri_105_1_0":{"x":"-36","y":"55"},"h_drk_ri_105_0_0":{"x":"-38","y":"59"},"h_drk_ri_106_3_0":{"x":"-26","y":"52"},"h_drk_ri_106_2_0":{"x":"-36","y":"54"},"h_drk_ri_106_4_0":{"x":"-7","y":"58"},"h_drk_ri_106_7_0":{"x":"-31","y":"65"},"h_drk_ri_106_0_0":{"x":"-42","y":"64"},"h_drk_ri_106_6_0":{"x":"-9","y":"65"},"h_drk_ri_106_5_0":{"x":"-3","y":"61"},"h_drk_ri_106_1_0":{"x":"-42","y":"57"},"h_crr_ri_106_5_0":{"x":"-9","y":"38"},"h_crr_ri_106_3_0":{"x":"-24","y":"33"},"h_crr_ri_106_4_0":{"x":"-1","y":"38"},"h_crr_ri_106_2_0":{"x":"-34","y":"32"},"h_crr_ri_106_1_0":{"x":"-43","y":"38"},"h_crr_ri_106_0_0":{"x":"-49","y":"43"},"h_sig_li_10_0_0":{"x":"-2","y":"113"},"h_sig_li_10_1_0":{"x":"-37","y":"111"},"h_sig_li_10_2_0":{"x":"-34","y":"112"},"h_sig_li_10_3_0":{"x":"-35","y":"107"},"h_sig_li_10_4_0":{"x":"-40","y":"108"},"h_sig_li_10_5_0":{"x":"-21","y":"110"},"h_sig_li_10_6_0":{"x":"3","y":"109"},"h_sig_li_10_7_0":{"x":"2","y":"102"},"h_sig_li_1_0_0":{"x":"-2","y":"113"},"h_sig_li_1_1_0":{"x":"-37","y":"111"},"h_sig_li_1_2_0":{"x":"-34","y":"112"},"h_sig_li_1_3_0":{"x":"-35","y":"107"},"h_sig_li_1_4_0":{"x":"-40","y":"108"},"h_sig_li_1_5_0":{"x":"-21","y":"110"},"h_sig_li_1_6_0":{"x":"3","y":"109"},"h_sig_li_1_7_0":{"x":"2","y":"102"},"h_sig_li_2_0_0":{"x":"-2","y":"113"},"h_sig_li_2_1_0":{"x":"-37","y":"111"},"h_sig_li_2_2_0":{"x":"-34","y":"112"},"h_sig_li_2_3_0":{"x":"-35","y":"107"},"h_sig_li_2_4_0":{"x":"-40","y":"108"},"h_sig_li_2_5_0":{"x":"-21","y":"110"},"h_sig_li_2_6_0":{"x":"3","y":"109"},"h_sig_li_2_7_0":{"x":"2","y":"102"},"h_sig_li_3_0_0":{"x":"-2","y":"113"},"h_sig_li_3_1_0":{"x":"-37","y":"111"},"h_sig_li_3_2_0":{"x":"-34","y":"112"},"h_sig_li_3_3_0":{"x":"-35","y":"107"},"h_sig_li_3_4_0":{"x":"-40","y":"108"},"h_sig_li_3_5_0":{"x":"-21","y":"110"},"h_sig_li_3_6_0":{"x":"3","y":"109"},"h_sig_li_3_7_0":{"x":"2","y":"102"},"h_sig_li_4_0_0":{"x":"-2","y":"113"},"h_sig_li_4_1_0":{"x":"-37","y":"111"},"h_sig_li_4_2_0":{"x":"-34","y":"112"},"h_sig_li_4_3_0":{"x":"-35","y":"107"},"h_sig_li_4_4_0":{"x":"-40","y":"108"},"h_sig_li_4_5_0":{"x":"-21","y":"110"},"h_sig_li_4_6_0":{"x":"3","y":"109"},"h_sig_li_4_7_0":{"x":"2","y":"102"},"h_sig_li_5_0_0":{"x":"-2","y":"113"},"h_sig_li_5_1_0":{"x":"-37","y":"111"},"h_sig_li_5_2_0":{"x":"-34","y":"112"},"h_sig_li_5_3_0":{"x":"-35","y":"107"},"h_sig_li_5_4_0":{"x":"-40","y":"108"},"h_sig_li_5_5_0":{"x":"-21","y":"110"},"h_sig_li_5_6_0":{"x":"3","y":"109"},"h_sig_li_5_7_0":{"x":"2","y":"102"},"h_sig_li_6_0_0":{"x":"-2","y":"113"},"h_sig_li_6_1_0":{"x":"-37","y":"111"},"h_sig_li_6_2_0":{"x":"-34","y":"112"},"h_sig_li_6_3_0":{"x":"-35","y":"107"},"h_sig_li_6_4_0":{"x":"-40","y":"108"},"h_sig_li_6_5_0":{"x":"-21","y":"110"},"h_sig_li_6_6_0":{"x":"3","y":"109"},"h_sig_li_6_7_0":{"x":"2","y":"102"},"h_sig_li_7_0_0":{"x":"-2","y":"113"},"h_sig_li_7_1_0":{"x":"-37","y":"111"},"h_sig_li_7_2_0":{"x":"-34","y":"112"},"h_sig_li_7_3_0":{"x":"-35","y":"107"},"h_sig_li_7_4_0":{"x":"-40","y":"108"},"h_sig_li_7_5_0":{"x":"-21","y":"110"},"h_sig_li_7_6_0":{"x":"3","y":"109"},"h_sig_li_7_7_0":{"x":"2","y":"102"},"h_sig_li_8_0_0":{"x":"-2","y":"113"},"h_sig_li_8_1_0":{"x":"-37","y":"111"},"h_sig_li_8_2_0":{"x":"-34","y":"112"},"h_sig_li_8_3_0":{"x":"-35","y":"107"},"h_sig_li_8_4_0":{"x":"-40","y":"108"},"h_sig_li_8_5_0":{"x":"-21","y":"110"},"h_sig_li_8_6_0":{"x":"3","y":"109"},"h_sig_li_8_7_0":{"x":"2","y":"102"},"h_sig_li_9_0_0":{"x":"-2","y":"113"},"h_sig_li_9_1_0":{"x":"-37","y":"111"},"h_sig_li_9_2_0":{"x":"-34","y":"112"},"h_sig_li_9_3_0":{"x":"-35","y":"107"},"h_sig_li_9_4_0":{"x":"-40","y":"108"},"h_sig_li_9_5_0":{"x":"-21","y":"110"},"h_sig_li_9_6_0":{"x":"3","y":"109"},"h_sig_li_9_7_0":{"x":"2","y":"102"},"h_sig_li_0_0_0":{"x":"-2","y":"113"},"h_sig_li_0_1_0":{"x":"-37","y":"111"},"h_sig_li_0_2_0":{"x":"-34","y":"112"},"h_sig_li_0_3_0":{"x":"-35","y":"107"},"h_sig_li_0_4_0":{"x":"-40","y":"108"},"h_sig_li_0_5_0":{"x":"-21","y":"110"},"h_sig_li_0_6_0":{"x":"3","y":"109"},"h_sig_li_0_7_0":{"x":"2","y":"102"},"h_sig_li_11_0_0":{"x":"-2","y":"113"},"h_sig_li_11_1_0":{"x":"-37","y":"111"},"h_sig_li_11_2_0":{"x":"-34","y":"112"},"h_sig_li_11_3_0":{"x":"-35","y":"107"},"h_sig_li_11_4_0":{"x":"-40","y":"108"},"h_sig_li_11_5_0":{"x":"-21","y":"110"},"h_sig_li_11_6_0":{"x":"3","y":"109"},"h_sig_li_11_7_0":{"x":"2","y":"102"},"h_sig_li_12_0_0":{"x":"-2","y":"113"},"h_sig_li_12_1_0":{"x":"-37","y":"111"},"h_sig_li_12_2_0":{"x":"-34","y":"112"},"h_sig_li_12_3_0":{"x":"-35","y":"107"},"h_sig_li_12_4_0":{"x":"-40","y":"108"},"h_sig_li_12_5_0":{"x":"-21","y":"110"},"h_sig_li_12_6_0":{"x":"3","y":"109"},"h_sig_li_12_7_0":{"x":"2","y":"102"},"h_sig_li_13_0_0":{"x":"-2","y":"113"},"h_sig_li_13_1_0":{"x":"-37","y":"111"},"h_sig_li_13_2_0":{"x":"-34","y":"112"},"h_sig_li_13_3_0":{"x":"-35","y":"107"},"h_sig_li_13_4_0":{"x":"-40","y":"108"},"h_sig_li_13_5_0":{"x":"-21","y":"110"},"h_sig_li_13_6_0":{"x":"3","y":"109"},"h_sig_li_13_7_0":{"x":"2","y":"102"},"h_sig_li_14_0_0":{"x":"-2","y":"113"},"h_sig_li_14_1_0":{"x":"-37","y":"111"},"h_sig_li_14_2_0":{"x":"-34","y":"112"},"h_sig_li_14_3_0":{"x":"-35","y":"107"},"h_sig_li_14_4_0":{"x":"-40","y":"108"},"h_sig_li_14_5_0":{"x":"-21","y":"110"},"h_sig_li_14_6_0":{"x":"3","y":"109"},"h_sig_li_14_7_0":{"x":"2","y":"102"},"h_sig_li_15_0_0":{"x":"-2","y":"113"},"h_sig_li_15_1_0":{"x":"-37","y":"111"},"h_sig_li_15_2_0":{"x":"-34","y":"112"},"h_sig_li_15_3_0":{"x":"-35","y":"107"},"h_sig_li_15_4_0":{"x":"-40","y":"108"},"h_sig_li_15_5_0":{"x":"-21","y":"110"},"h_sig_li_15_6_0":{"x":"3","y":"109"},"h_sig_li_15_7_0":{"x":"2","y":"102"},"h_sig_li_16_0_0":{"x":"-2","y":"113"},"h_sig_li_16_1_0":{"x":"-37","y":"111"},"h_sig_li_16_2_0":{"x":"-34","y":"112"},"h_sig_li_16_3_0":{"x":"-35","y":"107"},"h_sig_li_16_4_0":{"x":"-40","y":"108"},"h_sig_li_16_5_0":{"x":"-21","y":"110"},"h_sig_li_16_6_0":{"x":"3","y":"109"},"h_sig_li_16_7_0":{"x":"2","y":"102"},"h_sig_li_17_0_0":{"x":"-2","y":"113"},"h_sig_li_17_1_0":{"x":"-37","y":"111"},"h_sig_li_17_2_0":{"x":"-34","y":"112"},"h_sig_li_17_3_0":{"x":"-35","y":"107"},"h_sig_li_17_4_0":{"x":"-40","y":"108"},"h_sig_li_17_5_0":{"x":"-21","y":"110"},"h_sig_li_17_6_0":{"x":"3","y":"109"},"h_sig_li_17_7_0":{"x":"2","y":"102"}}