{"h_lay_ha_2710_2_0":{"x":"27","y":"39"},"h_lay_ha_2711_2_0":{"x":"15","y":"38"},"h_lsp_ha_2710_2_0":{"x":"-36","y":"-120"},"h_lsp_ha_2711_2_0":{"x":"-48","y":"-121"},"h_std_ha_2710_7_0":{"x":"-19","y":"77"},"h_std_ha_2710_3_0":{"x":"-19","y":"79"},"h_std_ha_2710_0_0":{"x":"-16","y":"77"},"h_std_ha_2710_1_0":{"x":"-18","y":"79"},"h_std_ha_2710_2_0":{"x":"-19","y":"80"},"h_std_ha_2711_7_0":{"x":"-21","y":"53"},"h_std_ha_2711_3_0":{"x":"-19","y":"72"},"h_std_ha_2711_0_0":{"x":"-22","y":"72"},"h_std_ha_2711_1_0":{"x":"-24","y":"74"},"h_std_ha_2711_2_0":{"x":"-21","y":"72"},"h_spk_ha_2710_7_0":{"x":"-19","y":"78"},"h_spk_ha_2710_3_0":{"x":"-19","y":"80"},"h_spk_ha_2710_0_0":{"x":"-16","y":"78"},"h_spk_ha_2710_1_0":{"x":"-18","y":"80"},"h_spk_ha_2710_2_0":{"x":"-19","y":"81"},"h_spk_ha_2711_7_0":{"x":"-21","y":"54"},"h_spk_ha_2711_3_0":{"x":"-19","y":"73"},"h_spk_ha_2711_0_0":{"x":"-22","y":"73"},"h_spk_ha_2711_1_0":{"x":"-24","y":"75"},"h_spk_ha_2711_2_0":{"x":"-21","y":"73"}}